package com.unionpay.sdk;

import android.content.BroadcastReceiver;
import android.content.Context;
import android.content.Intent;

final class ao extends BroadcastReceiver {
  ao(Object paramObject, Context paramContext) {}
  
  public final void onReceive(Context paramContext, Intent paramIntent) {
    // Byte code:
    //   0: aload_0
    //   1: getfield a : Ljava/lang/Object;
    //   4: astore_1
    //   5: aload_1
    //   6: monitorenter
    //   7: aload_0
    //   8: getfield a : Ljava/lang/Object;
    //   11: invokevirtual notifyAll : ()V
    //   14: aload_0
    //   15: getfield b : Landroid/content/Context;
    //   18: aload_0
    //   19: invokevirtual unregisterReceiver : (Landroid/content/BroadcastReceiver;)V
    //   22: aload_1
    //   23: monitorexit
    //   24: return
    //   25: astore_2
    //   26: aload_0
    //   27: getfield b : Landroid/content/Context;
    //   30: aload_0
    //   31: invokevirtual unregisterReceiver : (Landroid/content/BroadcastReceiver;)V
    //   34: goto -> 22
    //   37: astore_2
    //   38: aload_1
    //   39: monitorexit
    //   40: aload_2
    //   41: athrow
    //   42: astore_1
    //   43: goto -> 24
    //   46: astore_2
    //   47: aload_0
    //   48: getfield b : Landroid/content/Context;
    //   51: aload_0
    //   52: invokevirtual unregisterReceiver : (Landroid/content/BroadcastReceiver;)V
    //   55: aload_2
    //   56: athrow
    // Exception table:
    //   from	to	target	type
    //   0	7	42	java/lang/Throwable
    //   7	14	25	java/lang/Throwable
    //   7	14	46	finally
    //   14	22	37	finally
    //   22	24	37	finally
    //   26	34	37	finally
    //   38	42	42	java/lang/Throwable
    //   47	57	37	finally
  }
}


/* Location:              D:\Code\Crack\dex-tools-2.1-20190905-lanchon\zspns-pcgw-P36417A-0429-dex2jar.jar!\co\\unionpay\sdk\ao.class
 * Java compiler version: 6 (50.0)
 * JD-Core Version:       1.1.3
 */