package com.tencent.bugly;

import android.content.Context;
import com.tencent.bugly.crashreport.common.info.a;
import com.tencent.bugly.proguard.p;
import java.util.ArrayList;
import java.util.List;

public final class b {
  public static boolean a = true;
  
  public static List<a> b = new ArrayList<a>();
  
  public static boolean c;
  
  private static p d;
  
  private static boolean e;
  
  public static void a(Context paramContext) {
    // Byte code:
    //   0: ldc com/tencent/bugly/b
    //   2: monitorenter
    //   3: aload_0
    //   4: aconst_null
    //   5: invokestatic a : (Landroid/content/Context;Lcom/tencent/bugly/BuglyStrategy;)V
    //   8: ldc com/tencent/bugly/b
    //   10: monitorexit
    //   11: return
    //   12: astore_0
    //   13: ldc com/tencent/bugly/b
    //   15: monitorexit
    //   16: aload_0
    //   17: athrow
    // Exception table:
    //   from	to	target	type
    //   3	8	12	finally
  }
  
  public static void a(Context paramContext, BuglyStrategy paramBuglyStrategy) {
    // Byte code:
    //   0: ldc com/tencent/bugly/b
    //   2: monitorenter
    //   3: getstatic com/tencent/bugly/b.e : Z
    //   6: ifeq -> 23
    //   9: ldc '[init] initial Multi-times, ignore this.'
    //   11: iconst_0
    //   12: anewarray java/lang/Object
    //   15: invokestatic d : (Ljava/lang/String;[Ljava/lang/Object;)Z
    //   18: pop
    //   19: ldc com/tencent/bugly/b
    //   21: monitorexit
    //   22: return
    //   23: aload_0
    //   24: ifnonnull -> 40
    //   27: getstatic com/tencent/bugly/proguard/x.a : Ljava/lang/String;
    //   30: ldc '[init] context of init() is null, check it.'
    //   32: invokestatic w : (Ljava/lang/String;Ljava/lang/String;)I
    //   35: pop
    //   36: ldc com/tencent/bugly/b
    //   38: monitorexit
    //   39: return
    //   40: aload_0
    //   41: invokestatic a : (Landroid/content/Context;)Lcom/tencent/bugly/crashreport/common/info/a;
    //   44: astore_2
    //   45: aload_2
    //   46: invokestatic a : (Lcom/tencent/bugly/crashreport/common/info/a;)Z
    //   49: ifeq -> 60
    //   52: iconst_0
    //   53: putstatic com/tencent/bugly/b.a : Z
    //   56: ldc com/tencent/bugly/b
    //   58: monitorexit
    //   59: return
    //   60: aload_2
    //   61: invokevirtual f : ()Ljava/lang/String;
    //   64: astore_3
    //   65: aload_3
    //   66: ifnonnull -> 82
    //   69: getstatic com/tencent/bugly/proguard/x.a : Ljava/lang/String;
    //   72: ldc '[init] meta data of BUGLY_APPID in AndroidManifest.xml should be set.'
    //   74: invokestatic e : (Ljava/lang/String;Ljava/lang/String;)I
    //   77: pop
    //   78: ldc com/tencent/bugly/b
    //   80: monitorexit
    //   81: return
    //   82: aload_0
    //   83: aload_3
    //   84: aload_2
    //   85: getfield u : Z
    //   88: aload_1
    //   89: invokestatic a : (Landroid/content/Context;Ljava/lang/String;ZLcom/tencent/bugly/BuglyStrategy;)V
    //   92: ldc com/tencent/bugly/b
    //   94: monitorexit
    //   95: return
    //   96: astore_0
    //   97: ldc com/tencent/bugly/b
    //   99: monitorexit
    //   100: aload_0
    //   101: athrow
    // Exception table:
    //   from	to	target	type
    //   3	19	96	finally
    //   27	36	96	finally
    //   40	56	96	finally
    //   60	65	96	finally
    //   69	78	96	finally
    //   82	92	96	finally
  }
  
  public static void a(Context paramContext, String paramString, boolean paramBoolean, BuglyStrategy paramBuglyStrategy) {
    // Byte code:
    //   0: ldc com/tencent/bugly/b
    //   2: monitorenter
    //   3: getstatic com/tencent/bugly/b.e : Z
    //   6: ifeq -> 23
    //   9: ldc '[init] initial Multi-times, ignore this.'
    //   11: iconst_0
    //   12: anewarray java/lang/Object
    //   15: invokestatic d : (Ljava/lang/String;[Ljava/lang/Object;)Z
    //   18: pop
    //   19: ldc com/tencent/bugly/b
    //   21: monitorexit
    //   22: return
    //   23: aload_0
    //   24: ifnonnull -> 40
    //   27: getstatic com/tencent/bugly/proguard/x.a : Ljava/lang/String;
    //   30: ldc '[init] context is null, check it.'
    //   32: invokestatic w : (Ljava/lang/String;Ljava/lang/String;)I
    //   35: pop
    //   36: ldc com/tencent/bugly/b
    //   38: monitorexit
    //   39: return
    //   40: aload_1
    //   41: ifnonnull -> 57
    //   44: getstatic com/tencent/bugly/proguard/x.a : Ljava/lang/String;
    //   47: ldc 'init arg 'crashReportAppID' should not be null!'
    //   49: invokestatic e : (Ljava/lang/String;Ljava/lang/String;)I
    //   52: pop
    //   53: ldc com/tencent/bugly/b
    //   55: monitorexit
    //   56: return
    //   57: iconst_1
    //   58: putstatic com/tencent/bugly/b.e : Z
    //   61: iload_2
    //   62: ifeq -> 153
    //   65: iconst_1
    //   66: putstatic com/tencent/bugly/b.c : Z
    //   69: iconst_1
    //   70: putstatic com/tencent/bugly/proguard/x.b : Z
    //   73: ldc 'Bugly debug模式开启，请在发布时把isDebug关闭。 -- Running in debug model for 'isDebug' is enabled. Please disable it when you release.'
    //   75: iconst_0
    //   76: anewarray java/lang/Object
    //   79: invokestatic d : (Ljava/lang/String;[Ljava/lang/Object;)Z
    //   82: pop
    //   83: ldc '--------------------------------------------------------------------------------------------'
    //   85: iconst_0
    //   86: anewarray java/lang/Object
    //   89: invokestatic e : (Ljava/lang/String;[Ljava/lang/Object;)Z
    //   92: pop
    //   93: ldc 'Bugly debug模式将有以下行为特性 -- The following list shows the behaviour of debug model: '
    //   95: iconst_0
    //   96: anewarray java/lang/Object
    //   99: invokestatic d : (Ljava/lang/String;[Ljava/lang/Object;)Z
    //   102: pop
    //   103: ldc '[1] 输出详细的Bugly SDK的Log -- More detailed log of Bugly SDK will be output to logcat;'
    //   105: iconst_0
    //   106: anewarray java/lang/Object
    //   109: invokestatic d : (Ljava/lang/String;[Ljava/lang/Object;)Z
    //   112: pop
    //   113: ldc '[2] 每一条Crash都会被立即上报 -- Every crash caught by Bugly will be uploaded immediately.'
    //   115: iconst_0
    //   116: anewarray java/lang/Object
    //   119: invokestatic d : (Ljava/lang/String;[Ljava/lang/Object;)Z
    //   122: pop
    //   123: ldc '[3] 自定义日志将会在Logcat中输出 -- Custom log will be output to logcat.'
    //   125: iconst_0
    //   126: anewarray java/lang/Object
    //   129: invokestatic d : (Ljava/lang/String;[Ljava/lang/Object;)Z
    //   132: pop
    //   133: ldc '--------------------------------------------------------------------------------------------'
    //   135: iconst_0
    //   136: anewarray java/lang/Object
    //   139: invokestatic e : (Ljava/lang/String;[Ljava/lang/Object;)Z
    //   142: pop
    //   143: ldc '[init] Open debug mode of Bugly.'
    //   145: iconst_0
    //   146: anewarray java/lang/Object
    //   149: invokestatic b : (Ljava/lang/String;[Ljava/lang/Object;)Z
    //   152: pop
    //   153: ldc '[init] Bugly version: v%s'
    //   155: iconst_1
    //   156: anewarray java/lang/Object
    //   159: dup
    //   160: iconst_0
    //   161: ldc '3.1.0'
    //   163: aastore
    //   164: invokestatic a : (Ljava/lang/String;[Ljava/lang/Object;)Z
    //   167: pop
    //   168: ldc ' crash report start initializing...'
    //   170: iconst_0
    //   171: anewarray java/lang/Object
    //   174: invokestatic a : (Ljava/lang/String;[Ljava/lang/Object;)Z
    //   177: pop
    //   178: ldc '[init] Bugly start initializing...'
    //   180: iconst_0
    //   181: anewarray java/lang/Object
    //   184: invokestatic b : (Ljava/lang/String;[Ljava/lang/Object;)Z
    //   187: pop
    //   188: ldc '[init] Bugly complete version: v%s'
    //   190: iconst_1
    //   191: anewarray java/lang/Object
    //   194: dup
    //   195: iconst_0
    //   196: ldc '3.1.0'
    //   198: aastore
    //   199: invokestatic a : (Ljava/lang/String;[Ljava/lang/Object;)Z
    //   202: pop
    //   203: aload_0
    //   204: invokestatic a : (Landroid/content/Context;)Landroid/content/Context;
    //   207: astore #4
    //   209: aload #4
    //   211: invokestatic a : (Landroid/content/Context;)Lcom/tencent/bugly/crashreport/common/info/a;
    //   214: astore #5
    //   216: aload #5
    //   218: invokevirtual t : ()Ljava/lang/String;
    //   221: pop
    //   222: aload #4
    //   224: invokestatic a : (Landroid/content/Context;)V
    //   227: aload #4
    //   229: getstatic com/tencent/bugly/b.b : Ljava/util/List;
    //   232: invokestatic a : (Landroid/content/Context;Ljava/util/List;)Lcom/tencent/bugly/proguard/p;
    //   235: putstatic com/tencent/bugly/b.d : Lcom/tencent/bugly/proguard/p;
    //   238: aload #4
    //   240: invokestatic a : (Landroid/content/Context;)Lcom/tencent/bugly/proguard/u;
    //   243: pop
    //   244: aload #4
    //   246: getstatic com/tencent/bugly/b.b : Ljava/util/List;
    //   249: invokestatic a : (Landroid/content/Context;Ljava/util/List;)Lcom/tencent/bugly/crashreport/common/strategy/a;
    //   252: astore #6
    //   254: aload #4
    //   256: invokestatic a : (Landroid/content/Context;)Lcom/tencent/bugly/proguard/n;
    //   259: astore #7
    //   261: aload #5
    //   263: invokestatic a : (Lcom/tencent/bugly/crashreport/common/info/a;)Z
    //   266: ifeq -> 277
    //   269: iconst_0
    //   270: putstatic com/tencent/bugly/b.a : Z
    //   273: ldc com/tencent/bugly/b
    //   275: monitorexit
    //   276: return
    //   277: aload #5
    //   279: aload_1
    //   280: invokevirtual a : (Ljava/lang/String;)V
    //   283: ldc '[param] Set APP ID:%s'
    //   285: iconst_1
    //   286: anewarray java/lang/Object
    //   289: dup
    //   290: iconst_0
    //   291: aload_1
    //   292: aastore
    //   293: invokestatic a : (Ljava/lang/String;[Ljava/lang/Object;)Z
    //   296: pop
    //   297: aload_3
    //   298: ifnull -> 721
    //   301: aload_3
    //   302: invokevirtual getAppVersion : ()Ljava/lang/String;
    //   305: astore_1
    //   306: aload_1
    //   307: invokestatic isEmpty : (Ljava/lang/CharSequence;)Z
    //   310: ifne -> 381
    //   313: aload_1
    //   314: astore_0
    //   315: aload_1
    //   316: invokevirtual length : ()I
    //   319: bipush #100
    //   321: if_icmple -> 358
    //   324: aload_1
    //   325: iconst_0
    //   326: bipush #100
    //   328: invokevirtual substring : (II)Ljava/lang/String;
    //   331: astore_0
    //   332: ldc 'appVersion %s length is over limit %d substring to %s'
    //   334: iconst_3
    //   335: anewarray java/lang/Object
    //   338: dup
    //   339: iconst_0
    //   340: aload_1
    //   341: aastore
    //   342: dup
    //   343: iconst_1
    //   344: bipush #100
    //   346: invokestatic valueOf : (I)Ljava/lang/Integer;
    //   349: aastore
    //   350: dup
    //   351: iconst_2
    //   352: aload_0
    //   353: aastore
    //   354: invokestatic d : (Ljava/lang/String;[Ljava/lang/Object;)Z
    //   357: pop
    //   358: aload #5
    //   360: aload_0
    //   361: putfield j : Ljava/lang/String;
    //   364: ldc '[param] Set App version: %s'
    //   366: iconst_1
    //   367: anewarray java/lang/Object
    //   370: dup
    //   371: iconst_0
    //   372: aload_3
    //   373: invokevirtual getAppVersion : ()Ljava/lang/String;
    //   376: aastore
    //   377: invokestatic a : (Ljava/lang/String;[Ljava/lang/Object;)Z
    //   380: pop
    //   381: aload_3
    //   382: invokevirtual isReplaceOldChannel : ()Z
    //   385: ifeq -> 472
    //   388: aload_3
    //   389: invokevirtual getAppChannel : ()Ljava/lang/String;
    //   392: astore_1
    //   393: aload_1
    //   394: invokestatic isEmpty : (Ljava/lang/CharSequence;)Z
    //   397: ifne -> 519
    //   400: aload_1
    //   401: astore_0
    //   402: aload_1
    //   403: invokevirtual length : ()I
    //   406: bipush #100
    //   408: if_icmple -> 445
    //   411: aload_1
    //   412: iconst_0
    //   413: bipush #100
    //   415: invokevirtual substring : (II)Ljava/lang/String;
    //   418: astore_0
    //   419: ldc 'appChannel %s length is over limit %d substring to %s'
    //   421: iconst_3
    //   422: anewarray java/lang/Object
    //   425: dup
    //   426: iconst_0
    //   427: aload_1
    //   428: aastore
    //   429: dup
    //   430: iconst_1
    //   431: bipush #100
    //   433: invokestatic valueOf : (I)Ljava/lang/Integer;
    //   436: aastore
    //   437: dup
    //   438: iconst_2
    //   439: aload_0
    //   440: aastore
    //   441: invokestatic d : (Ljava/lang/String;[Ljava/lang/Object;)Z
    //   444: pop
    //   445: getstatic com/tencent/bugly/b.d : Lcom/tencent/bugly/proguard/p;
    //   448: sipush #556
    //   451: ldc 'app_channel'
    //   453: aload_0
    //   454: invokevirtual getBytes : ()[B
    //   457: aconst_null
    //   458: iconst_0
    //   459: invokevirtual a : (ILjava/lang/String;[BLcom/tencent/bugly/proguard/o;Z)Z
    //   462: pop
    //   463: aload #5
    //   465: aload_0
    //   466: putfield l : Ljava/lang/String;
    //   469: goto -> 519
    //   472: getstatic com/tencent/bugly/b.d : Lcom/tencent/bugly/proguard/p;
    //   475: sipush #556
    //   478: aconst_null
    //   479: iconst_1
    //   480: invokevirtual a : (ILcom/tencent/bugly/proguard/o;Z)Ljava/util/Map;
    //   483: astore_0
    //   484: aload_0
    //   485: ifnull -> 519
    //   488: aload_0
    //   489: ldc 'app_channel'
    //   491: invokeinterface get : (Ljava/lang/Object;)Ljava/lang/Object;
    //   496: checkcast [B
    //   499: astore_1
    //   500: aload_1
    //   501: ifnull -> 519
    //   504: new java/lang/String
    //   507: astore_0
    //   508: aload_0
    //   509: aload_1
    //   510: invokespecial <init> : ([B)V
    //   513: aload #5
    //   515: aload_0
    //   516: putfield l : Ljava/lang/String;
    //   519: ldc '[param] Set App channel: %s'
    //   521: iconst_1
    //   522: anewarray java/lang/Object
    //   525: dup
    //   526: iconst_0
    //   527: aload #5
    //   529: getfield l : Ljava/lang/String;
    //   532: aastore
    //   533: invokestatic a : (Ljava/lang/String;[Ljava/lang/Object;)Z
    //   536: pop
    //   537: goto -> 551
    //   540: astore_0
    //   541: getstatic com/tencent/bugly/b.c : Z
    //   544: ifeq -> 551
    //   547: aload_0
    //   548: invokevirtual printStackTrace : ()V
    //   551: aload_3
    //   552: invokevirtual getAppPackageName : ()Ljava/lang/String;
    //   555: astore_1
    //   556: aload_1
    //   557: invokestatic isEmpty : (Ljava/lang/CharSequence;)Z
    //   560: ifne -> 631
    //   563: aload_1
    //   564: astore_0
    //   565: aload_1
    //   566: invokevirtual length : ()I
    //   569: bipush #100
    //   571: if_icmple -> 608
    //   574: aload_1
    //   575: iconst_0
    //   576: bipush #100
    //   578: invokevirtual substring : (II)Ljava/lang/String;
    //   581: astore_0
    //   582: ldc 'appPackageName %s length is over limit %d substring to %s'
    //   584: iconst_3
    //   585: anewarray java/lang/Object
    //   588: dup
    //   589: iconst_0
    //   590: aload_1
    //   591: aastore
    //   592: dup
    //   593: iconst_1
    //   594: bipush #100
    //   596: invokestatic valueOf : (I)Ljava/lang/Integer;
    //   599: aastore
    //   600: dup
    //   601: iconst_2
    //   602: aload_0
    //   603: aastore
    //   604: invokestatic d : (Ljava/lang/String;[Ljava/lang/Object;)Z
    //   607: pop
    //   608: aload #5
    //   610: aload_0
    //   611: putfield c : Ljava/lang/String;
    //   614: ldc '[param] Set App package: %s'
    //   616: iconst_1
    //   617: anewarray java/lang/Object
    //   620: dup
    //   621: iconst_0
    //   622: aload_3
    //   623: invokevirtual getAppPackageName : ()Ljava/lang/String;
    //   626: aastore
    //   627: invokestatic a : (Ljava/lang/String;[Ljava/lang/Object;)Z
    //   630: pop
    //   631: aload_3
    //   632: invokevirtual getDeviceID : ()Ljava/lang/String;
    //   635: astore_1
    //   636: aload_1
    //   637: ifnull -> 705
    //   640: aload_1
    //   641: astore_0
    //   642: aload_1
    //   643: invokevirtual length : ()I
    //   646: bipush #100
    //   648: if_icmple -> 685
    //   651: aload_1
    //   652: iconst_0
    //   653: bipush #100
    //   655: invokevirtual substring : (II)Ljava/lang/String;
    //   658: astore_0
    //   659: ldc 'deviceId %s length is over limit %d substring to %s'
    //   661: iconst_3
    //   662: anewarray java/lang/Object
    //   665: dup
    //   666: iconst_0
    //   667: aload_1
    //   668: aastore
    //   669: dup
    //   670: iconst_1
    //   671: bipush #100
    //   673: invokestatic valueOf : (I)Ljava/lang/Integer;
    //   676: aastore
    //   677: dup
    //   678: iconst_2
    //   679: aload_0
    //   680: aastore
    //   681: invokestatic d : (Ljava/lang/String;[Ljava/lang/Object;)Z
    //   684: pop
    //   685: aload #5
    //   687: aload_0
    //   688: invokevirtual c : (Ljava/lang/String;)V
    //   691: ldc '[param] Set device ID: %s'
    //   693: iconst_1
    //   694: anewarray java/lang/Object
    //   697: dup
    //   698: iconst_0
    //   699: aload_0
    //   700: aastore
    //   701: invokestatic a : (Ljava/lang/String;[Ljava/lang/Object;)Z
    //   704: pop
    //   705: aload #5
    //   707: aload_3
    //   708: invokevirtual isUploadProcess : ()Z
    //   711: putfield e : Z
    //   714: aload_3
    //   715: invokevirtual isBuglyLogUpload : ()Z
    //   718: putstatic com/tencent/bugly/proguard/y.a : Z
    //   721: aload #4
    //   723: aload_3
    //   724: invokestatic a : (Landroid/content/Context;Lcom/tencent/bugly/BuglyStrategy;)V
    //   727: iconst_0
    //   728: istore #8
    //   730: getstatic com/tencent/bugly/b.b : Ljava/util/List;
    //   733: invokeinterface size : ()I
    //   738: istore #9
    //   740: iload #8
    //   742: iload #9
    //   744: if_icmpge -> 812
    //   747: aload #7
    //   749: getstatic com/tencent/bugly/b.b : Ljava/util/List;
    //   752: iload #8
    //   754: invokeinterface get : (I)Ljava/lang/Object;
    //   759: checkcast com/tencent/bugly/a
    //   762: getfield id : I
    //   765: invokevirtual a : (I)Z
    //   768: ifeq -> 806
    //   771: getstatic com/tencent/bugly/b.b : Ljava/util/List;
    //   774: iload #8
    //   776: invokeinterface get : (I)Ljava/lang/Object;
    //   781: checkcast com/tencent/bugly/a
    //   784: aload #4
    //   786: iload_2
    //   787: aload_3
    //   788: invokevirtual init : (Landroid/content/Context;ZLcom/tencent/bugly/BuglyStrategy;)V
    //   791: goto -> 806
    //   794: astore_0
    //   795: aload_0
    //   796: invokestatic a : (Ljava/lang/Throwable;)Z
    //   799: ifne -> 806
    //   802: aload_0
    //   803: invokevirtual printStackTrace : ()V
    //   806: iinc #8, 1
    //   809: goto -> 730
    //   812: aload_3
    //   813: ifnull -> 825
    //   816: aload_3
    //   817: invokevirtual getAppReportDelay : ()J
    //   820: lstore #10
    //   822: goto -> 828
    //   825: lconst_0
    //   826: lstore #10
    //   828: aload #6
    //   830: lload #10
    //   832: invokevirtual a : (J)V
    //   835: ldc_w '[init] Bugly initialization finished.'
    //   838: iconst_0
    //   839: anewarray java/lang/Object
    //   842: invokestatic b : (Ljava/lang/String;[Ljava/lang/Object;)Z
    //   845: pop
    //   846: ldc com/tencent/bugly/b
    //   848: monitorexit
    //   849: return
    //   850: astore_0
    //   851: ldc com/tencent/bugly/b
    //   853: monitorexit
    //   854: aload_0
    //   855: athrow
    // Exception table:
    //   from	to	target	type
    //   3	19	850	finally
    //   27	36	850	finally
    //   44	53	850	finally
    //   57	61	850	finally
    //   65	153	850	finally
    //   153	273	850	finally
    //   277	297	850	finally
    //   301	313	850	finally
    //   315	358	850	finally
    //   358	381	850	finally
    //   381	400	540	java/lang/Exception
    //   381	400	850	finally
    //   402	445	540	java/lang/Exception
    //   402	445	850	finally
    //   445	469	540	java/lang/Exception
    //   445	469	850	finally
    //   472	484	540	java/lang/Exception
    //   472	484	850	finally
    //   488	500	540	java/lang/Exception
    //   488	500	850	finally
    //   504	519	540	java/lang/Exception
    //   504	519	850	finally
    //   519	537	540	java/lang/Exception
    //   519	537	850	finally
    //   541	551	850	finally
    //   551	563	850	finally
    //   565	608	850	finally
    //   608	631	850	finally
    //   631	636	850	finally
    //   642	685	850	finally
    //   685	705	850	finally
    //   705	721	850	finally
    //   721	727	850	finally
    //   730	740	850	finally
    //   747	791	794	java/lang/Throwable
    //   747	791	850	finally
    //   795	806	850	finally
    //   816	822	850	finally
    //   828	846	850	finally
  }
  
  public static void a(a parama) {
    // Byte code:
    //   0: ldc com/tencent/bugly/b
    //   2: monitorenter
    //   3: getstatic com/tencent/bugly/b.b : Ljava/util/List;
    //   6: aload_0
    //   7: invokeinterface contains : (Ljava/lang/Object;)Z
    //   12: ifne -> 25
    //   15: getstatic com/tencent/bugly/b.b : Ljava/util/List;
    //   18: aload_0
    //   19: invokeinterface add : (Ljava/lang/Object;)Z
    //   24: pop
    //   25: ldc com/tencent/bugly/b
    //   27: monitorexit
    //   28: return
    //   29: astore_0
    //   30: ldc com/tencent/bugly/b
    //   32: monitorexit
    //   33: aload_0
    //   34: athrow
    // Exception table:
    //   from	to	target	type
    //   3	25	29	finally
  }
  
  private static boolean a(a parama) {
    List list = parama.o;
    parama.getClass();
    return (list != null && list.contains("bugly"));
  }
}


/* Location:              D:\Code\Crack\dex-tools-2.1-20190905-lanchon\zspns-pcgw-P36417A-0429-dex2jar.jar!\com\tencent\bugly\b.class
 * Java compiler version: 6 (50.0)
 * JD-Core Version:       1.1.3
 */