package org.apache.http.impl.client;

import java.io.IOException;
import org.apache.http.ConnectionReuseStrategy;
import org.apache.http.HttpHost;
import org.apache.http.HttpRequest;
import org.apache.http.HttpRequestInterceptor;
import org.apache.http.HttpResponse;
import org.apache.http.HttpResponseInterceptor;
import org.apache.http.auth.AuthSchemeRegistry;
import org.apache.http.client.AuthenticationHandler;
import org.apache.http.client.ClientProtocolException;
import org.apache.http.client.CookieStore;
import org.apache.http.client.CredentialsProvider;
import org.apache.http.client.HttpClient;
import org.apache.http.client.HttpRequestRetryHandler;
import org.apache.http.client.RedirectHandler;
import org.apache.http.client.RequestDirector;
import org.apache.http.client.ResponseHandler;
import org.apache.http.client.UserTokenHandler;
import org.apache.http.client.methods.HttpUriRequest;
import org.apache.http.conn.ClientConnectionManager;
import org.apache.http.conn.ConnectionKeepAliveStrategy;
import org.apache.http.conn.routing.HttpRoutePlanner;
import org.apache.http.cookie.CookieSpecRegistry;
import org.apache.http.params.HttpParams;
import org.apache.http.protocol.BasicHttpProcessor;
import org.apache.http.protocol.HttpContext;
import org.apache.http.protocol.HttpProcessor;
import org.apache.http.protocol.HttpRequestExecutor;

@Deprecated
public abstract class AbstractHttpClient implements HttpClient {
  protected AbstractHttpClient(ClientConnectionManager paramClientConnectionManager, HttpParams paramHttpParams) {
    throw new RuntimeException("Stub!");
  }
  
  public void addRequestInterceptor(HttpRequestInterceptor paramHttpRequestInterceptor) {
    // Byte code:
    //   0: aload_0
    //   1: monitorenter
    //   2: new java/lang/RuntimeException
    //   5: astore_1
    //   6: aload_1
    //   7: ldc 'Stub!'
    //   9: invokespecial <init> : (Ljava/lang/String;)V
    //   12: aload_1
    //   13: athrow
    //   14: astore_1
    //   15: aload_0
    //   16: monitorexit
    //   17: aload_1
    //   18: athrow
    // Exception table:
    //   from	to	target	type
    //   2	14	14	finally
  }
  
  public void addRequestInterceptor(HttpRequestInterceptor paramHttpRequestInterceptor, int paramInt) {
    // Byte code:
    //   0: aload_0
    //   1: monitorenter
    //   2: new java/lang/RuntimeException
    //   5: astore_1
    //   6: aload_1
    //   7: ldc 'Stub!'
    //   9: invokespecial <init> : (Ljava/lang/String;)V
    //   12: aload_1
    //   13: athrow
    //   14: astore_1
    //   15: aload_0
    //   16: monitorexit
    //   17: aload_1
    //   18: athrow
    // Exception table:
    //   from	to	target	type
    //   2	14	14	finally
  }
  
  public void addResponseInterceptor(HttpResponseInterceptor paramHttpResponseInterceptor) {
    // Byte code:
    //   0: aload_0
    //   1: monitorenter
    //   2: new java/lang/RuntimeException
    //   5: astore_1
    //   6: aload_1
    //   7: ldc 'Stub!'
    //   9: invokespecial <init> : (Ljava/lang/String;)V
    //   12: aload_1
    //   13: athrow
    //   14: astore_1
    //   15: aload_0
    //   16: monitorexit
    //   17: aload_1
    //   18: athrow
    // Exception table:
    //   from	to	target	type
    //   2	14	14	finally
  }
  
  public void addResponseInterceptor(HttpResponseInterceptor paramHttpResponseInterceptor, int paramInt) {
    // Byte code:
    //   0: aload_0
    //   1: monitorenter
    //   2: new java/lang/RuntimeException
    //   5: astore_1
    //   6: aload_1
    //   7: ldc 'Stub!'
    //   9: invokespecial <init> : (Ljava/lang/String;)V
    //   12: aload_1
    //   13: athrow
    //   14: astore_1
    //   15: aload_0
    //   16: monitorexit
    //   17: aload_1
    //   18: athrow
    // Exception table:
    //   from	to	target	type
    //   2	14	14	finally
  }
  
  public void clearRequestInterceptors() {
    // Byte code:
    //   0: aload_0
    //   1: monitorenter
    //   2: new java/lang/RuntimeException
    //   5: astore_1
    //   6: aload_1
    //   7: ldc 'Stub!'
    //   9: invokespecial <init> : (Ljava/lang/String;)V
    //   12: aload_1
    //   13: athrow
    //   14: astore_1
    //   15: aload_0
    //   16: monitorexit
    //   17: aload_1
    //   18: athrow
    // Exception table:
    //   from	to	target	type
    //   2	14	14	finally
  }
  
  public void clearResponseInterceptors() {
    // Byte code:
    //   0: aload_0
    //   1: monitorenter
    //   2: new java/lang/RuntimeException
    //   5: astore_1
    //   6: aload_1
    //   7: ldc 'Stub!'
    //   9: invokespecial <init> : (Ljava/lang/String;)V
    //   12: aload_1
    //   13: athrow
    //   14: astore_1
    //   15: aload_0
    //   16: monitorexit
    //   17: aload_1
    //   18: athrow
    // Exception table:
    //   from	to	target	type
    //   2	14	14	finally
  }
  
  protected abstract AuthSchemeRegistry createAuthSchemeRegistry();
  
  protected abstract ClientConnectionManager createClientConnectionManager();
  
  protected RequestDirector createClientRequestDirector(HttpRequestExecutor paramHttpRequestExecutor, ClientConnectionManager paramClientConnectionManager, ConnectionReuseStrategy paramConnectionReuseStrategy, ConnectionKeepAliveStrategy paramConnectionKeepAliveStrategy, HttpRoutePlanner paramHttpRoutePlanner, HttpProcessor paramHttpProcessor, HttpRequestRetryHandler paramHttpRequestRetryHandler, RedirectHandler paramRedirectHandler, AuthenticationHandler paramAuthenticationHandler1, AuthenticationHandler paramAuthenticationHandler2, UserTokenHandler paramUserTokenHandler, HttpParams paramHttpParams) {
    throw new RuntimeException("Stub!");
  }
  
  protected abstract ConnectionKeepAliveStrategy createConnectionKeepAliveStrategy();
  
  protected abstract ConnectionReuseStrategy createConnectionReuseStrategy();
  
  protected abstract CookieSpecRegistry createCookieSpecRegistry();
  
  protected abstract CookieStore createCookieStore();
  
  protected abstract CredentialsProvider createCredentialsProvider();
  
  protected abstract HttpContext createHttpContext();
  
  protected abstract HttpParams createHttpParams();
  
  protected abstract BasicHttpProcessor createHttpProcessor();
  
  protected abstract HttpRequestRetryHandler createHttpRequestRetryHandler();
  
  protected abstract HttpRoutePlanner createHttpRoutePlanner();
  
  protected abstract AuthenticationHandler createProxyAuthenticationHandler();
  
  protected abstract RedirectHandler createRedirectHandler();
  
  protected abstract HttpRequestExecutor createRequestExecutor();
  
  protected abstract AuthenticationHandler createTargetAuthenticationHandler();
  
  protected abstract UserTokenHandler createUserTokenHandler();
  
  protected HttpParams determineParams(HttpRequest paramHttpRequest) {
    throw new RuntimeException("Stub!");
  }
  
  public <T> T execute(HttpHost paramHttpHost, HttpRequest paramHttpRequest, ResponseHandler<? extends T> paramResponseHandler) throws IOException, ClientProtocolException {
    throw new RuntimeException("Stub!");
  }
  
  public <T> T execute(HttpHost paramHttpHost, HttpRequest paramHttpRequest, ResponseHandler<? extends T> paramResponseHandler, HttpContext paramHttpContext) throws IOException, ClientProtocolException {
    throw new RuntimeException("Stub!");
  }
  
  public <T> T execute(HttpUriRequest paramHttpUriRequest, ResponseHandler<? extends T> paramResponseHandler) throws IOException, ClientProtocolException {
    throw new RuntimeException("Stub!");
  }
  
  public <T> T execute(HttpUriRequest paramHttpUriRequest, ResponseHandler<? extends T> paramResponseHandler, HttpContext paramHttpContext) throws IOException, ClientProtocolException {
    throw new RuntimeException("Stub!");
  }
  
  public final HttpResponse execute(HttpHost paramHttpHost, HttpRequest paramHttpRequest) throws IOException, ClientProtocolException {
    throw new RuntimeException("Stub!");
  }
  
  public final HttpResponse execute(HttpHost paramHttpHost, HttpRequest paramHttpRequest, HttpContext paramHttpContext) throws IOException, ClientProtocolException {
    throw new RuntimeException("Stub!");
  }
  
  public final HttpResponse execute(HttpUriRequest paramHttpUriRequest) throws IOException, ClientProtocolException {
    throw new RuntimeException("Stub!");
  }
  
  public final HttpResponse execute(HttpUriRequest paramHttpUriRequest, HttpContext paramHttpContext) throws IOException, ClientProtocolException {
    throw new RuntimeException("Stub!");
  }
  
  public final AuthSchemeRegistry getAuthSchemes() {
    // Byte code:
    //   0: aload_0
    //   1: monitorenter
    //   2: new java/lang/RuntimeException
    //   5: astore_1
    //   6: aload_1
    //   7: ldc 'Stub!'
    //   9: invokespecial <init> : (Ljava/lang/String;)V
    //   12: aload_1
    //   13: athrow
    //   14: astore_1
    //   15: aload_0
    //   16: monitorexit
    //   17: aload_1
    //   18: athrow
    // Exception table:
    //   from	to	target	type
    //   2	14	14	finally
  }
  
  public final ConnectionKeepAliveStrategy getConnectionKeepAliveStrategy() {
    // Byte code:
    //   0: aload_0
    //   1: monitorenter
    //   2: new java/lang/RuntimeException
    //   5: astore_1
    //   6: aload_1
    //   7: ldc 'Stub!'
    //   9: invokespecial <init> : (Ljava/lang/String;)V
    //   12: aload_1
    //   13: athrow
    //   14: astore_1
    //   15: aload_0
    //   16: monitorexit
    //   17: aload_1
    //   18: athrow
    // Exception table:
    //   from	to	target	type
    //   2	14	14	finally
  }
  
  public final ClientConnectionManager getConnectionManager() {
    // Byte code:
    //   0: aload_0
    //   1: monitorenter
    //   2: new java/lang/RuntimeException
    //   5: astore_1
    //   6: aload_1
    //   7: ldc 'Stub!'
    //   9: invokespecial <init> : (Ljava/lang/String;)V
    //   12: aload_1
    //   13: athrow
    //   14: astore_1
    //   15: aload_0
    //   16: monitorexit
    //   17: aload_1
    //   18: athrow
    // Exception table:
    //   from	to	target	type
    //   2	14	14	finally
  }
  
  public final ConnectionReuseStrategy getConnectionReuseStrategy() {
    // Byte code:
    //   0: aload_0
    //   1: monitorenter
    //   2: new java/lang/RuntimeException
    //   5: astore_1
    //   6: aload_1
    //   7: ldc 'Stub!'
    //   9: invokespecial <init> : (Ljava/lang/String;)V
    //   12: aload_1
    //   13: athrow
    //   14: astore_1
    //   15: aload_0
    //   16: monitorexit
    //   17: aload_1
    //   18: athrow
    // Exception table:
    //   from	to	target	type
    //   2	14	14	finally
  }
  
  public final CookieSpecRegistry getCookieSpecs() {
    // Byte code:
    //   0: aload_0
    //   1: monitorenter
    //   2: new java/lang/RuntimeException
    //   5: astore_1
    //   6: aload_1
    //   7: ldc 'Stub!'
    //   9: invokespecial <init> : (Ljava/lang/String;)V
    //   12: aload_1
    //   13: athrow
    //   14: astore_1
    //   15: aload_0
    //   16: monitorexit
    //   17: aload_1
    //   18: athrow
    // Exception table:
    //   from	to	target	type
    //   2	14	14	finally
  }
  
  public final CookieStore getCookieStore() {
    // Byte code:
    //   0: aload_0
    //   1: monitorenter
    //   2: new java/lang/RuntimeException
    //   5: astore_1
    //   6: aload_1
    //   7: ldc 'Stub!'
    //   9: invokespecial <init> : (Ljava/lang/String;)V
    //   12: aload_1
    //   13: athrow
    //   14: astore_1
    //   15: aload_0
    //   16: monitorexit
    //   17: aload_1
    //   18: athrow
    // Exception table:
    //   from	to	target	type
    //   2	14	14	finally
  }
  
  public final CredentialsProvider getCredentialsProvider() {
    // Byte code:
    //   0: aload_0
    //   1: monitorenter
    //   2: new java/lang/RuntimeException
    //   5: astore_1
    //   6: aload_1
    //   7: ldc 'Stub!'
    //   9: invokespecial <init> : (Ljava/lang/String;)V
    //   12: aload_1
    //   13: athrow
    //   14: astore_1
    //   15: aload_0
    //   16: monitorexit
    //   17: aload_1
    //   18: athrow
    // Exception table:
    //   from	to	target	type
    //   2	14	14	finally
  }
  
  protected final BasicHttpProcessor getHttpProcessor() {
    // Byte code:
    //   0: aload_0
    //   1: monitorenter
    //   2: new java/lang/RuntimeException
    //   5: astore_1
    //   6: aload_1
    //   7: ldc 'Stub!'
    //   9: invokespecial <init> : (Ljava/lang/String;)V
    //   12: aload_1
    //   13: athrow
    //   14: astore_1
    //   15: aload_0
    //   16: monitorexit
    //   17: aload_1
    //   18: athrow
    // Exception table:
    //   from	to	target	type
    //   2	14	14	finally
  }
  
  public final HttpRequestRetryHandler getHttpRequestRetryHandler() {
    // Byte code:
    //   0: aload_0
    //   1: monitorenter
    //   2: new java/lang/RuntimeException
    //   5: astore_1
    //   6: aload_1
    //   7: ldc 'Stub!'
    //   9: invokespecial <init> : (Ljava/lang/String;)V
    //   12: aload_1
    //   13: athrow
    //   14: astore_1
    //   15: aload_0
    //   16: monitorexit
    //   17: aload_1
    //   18: athrow
    // Exception table:
    //   from	to	target	type
    //   2	14	14	finally
  }
  
  public final HttpParams getParams() {
    // Byte code:
    //   0: aload_0
    //   1: monitorenter
    //   2: new java/lang/RuntimeException
    //   5: astore_1
    //   6: aload_1
    //   7: ldc 'Stub!'
    //   9: invokespecial <init> : (Ljava/lang/String;)V
    //   12: aload_1
    //   13: athrow
    //   14: astore_1
    //   15: aload_0
    //   16: monitorexit
    //   17: aload_1
    //   18: athrow
    // Exception table:
    //   from	to	target	type
    //   2	14	14	finally
  }
  
  public final AuthenticationHandler getProxyAuthenticationHandler() {
    // Byte code:
    //   0: aload_0
    //   1: monitorenter
    //   2: new java/lang/RuntimeException
    //   5: astore_1
    //   6: aload_1
    //   7: ldc 'Stub!'
    //   9: invokespecial <init> : (Ljava/lang/String;)V
    //   12: aload_1
    //   13: athrow
    //   14: astore_1
    //   15: aload_0
    //   16: monitorexit
    //   17: aload_1
    //   18: athrow
    // Exception table:
    //   from	to	target	type
    //   2	14	14	finally
  }
  
  public final RedirectHandler getRedirectHandler() {
    // Byte code:
    //   0: aload_0
    //   1: monitorenter
    //   2: new java/lang/RuntimeException
    //   5: astore_1
    //   6: aload_1
    //   7: ldc 'Stub!'
    //   9: invokespecial <init> : (Ljava/lang/String;)V
    //   12: aload_1
    //   13: athrow
    //   14: astore_1
    //   15: aload_0
    //   16: monitorexit
    //   17: aload_1
    //   18: athrow
    // Exception table:
    //   from	to	target	type
    //   2	14	14	finally
  }
  
  public final HttpRequestExecutor getRequestExecutor() {
    // Byte code:
    //   0: aload_0
    //   1: monitorenter
    //   2: new java/lang/RuntimeException
    //   5: astore_1
    //   6: aload_1
    //   7: ldc 'Stub!'
    //   9: invokespecial <init> : (Ljava/lang/String;)V
    //   12: aload_1
    //   13: athrow
    //   14: astore_1
    //   15: aload_0
    //   16: monitorexit
    //   17: aload_1
    //   18: athrow
    // Exception table:
    //   from	to	target	type
    //   2	14	14	finally
  }
  
  public HttpRequestInterceptor getRequestInterceptor(int paramInt) {
    // Byte code:
    //   0: aload_0
    //   1: monitorenter
    //   2: new java/lang/RuntimeException
    //   5: astore_2
    //   6: aload_2
    //   7: ldc 'Stub!'
    //   9: invokespecial <init> : (Ljava/lang/String;)V
    //   12: aload_2
    //   13: athrow
    //   14: astore_2
    //   15: aload_0
    //   16: monitorexit
    //   17: aload_2
    //   18: athrow
    // Exception table:
    //   from	to	target	type
    //   2	14	14	finally
  }
  
  public int getRequestInterceptorCount() {
    // Byte code:
    //   0: aload_0
    //   1: monitorenter
    //   2: new java/lang/RuntimeException
    //   5: astore_1
    //   6: aload_1
    //   7: ldc 'Stub!'
    //   9: invokespecial <init> : (Ljava/lang/String;)V
    //   12: aload_1
    //   13: athrow
    //   14: astore_1
    //   15: aload_0
    //   16: monitorexit
    //   17: aload_1
    //   18: athrow
    // Exception table:
    //   from	to	target	type
    //   2	14	14	finally
  }
  
  public HttpResponseInterceptor getResponseInterceptor(int paramInt) {
    // Byte code:
    //   0: aload_0
    //   1: monitorenter
    //   2: new java/lang/RuntimeException
    //   5: astore_2
    //   6: aload_2
    //   7: ldc 'Stub!'
    //   9: invokespecial <init> : (Ljava/lang/String;)V
    //   12: aload_2
    //   13: athrow
    //   14: astore_2
    //   15: aload_0
    //   16: monitorexit
    //   17: aload_2
    //   18: athrow
    // Exception table:
    //   from	to	target	type
    //   2	14	14	finally
  }
  
  public int getResponseInterceptorCount() {
    // Byte code:
    //   0: aload_0
    //   1: monitorenter
    //   2: new java/lang/RuntimeException
    //   5: astore_1
    //   6: aload_1
    //   7: ldc 'Stub!'
    //   9: invokespecial <init> : (Ljava/lang/String;)V
    //   12: aload_1
    //   13: athrow
    //   14: astore_1
    //   15: aload_0
    //   16: monitorexit
    //   17: aload_1
    //   18: athrow
    // Exception table:
    //   from	to	target	type
    //   2	14	14	finally
  }
  
  public final HttpRoutePlanner getRoutePlanner() {
    // Byte code:
    //   0: aload_0
    //   1: monitorenter
    //   2: new java/lang/RuntimeException
    //   5: astore_1
    //   6: aload_1
    //   7: ldc 'Stub!'
    //   9: invokespecial <init> : (Ljava/lang/String;)V
    //   12: aload_1
    //   13: athrow
    //   14: astore_1
    //   15: aload_0
    //   16: monitorexit
    //   17: aload_1
    //   18: athrow
    // Exception table:
    //   from	to	target	type
    //   2	14	14	finally
  }
  
  public final AuthenticationHandler getTargetAuthenticationHandler() {
    // Byte code:
    //   0: aload_0
    //   1: monitorenter
    //   2: new java/lang/RuntimeException
    //   5: astore_1
    //   6: aload_1
    //   7: ldc 'Stub!'
    //   9: invokespecial <init> : (Ljava/lang/String;)V
    //   12: aload_1
    //   13: athrow
    //   14: astore_1
    //   15: aload_0
    //   16: monitorexit
    //   17: aload_1
    //   18: athrow
    // Exception table:
    //   from	to	target	type
    //   2	14	14	finally
  }
  
  public final UserTokenHandler getUserTokenHandler() {
    // Byte code:
    //   0: aload_0
    //   1: monitorenter
    //   2: new java/lang/RuntimeException
    //   5: astore_1
    //   6: aload_1
    //   7: ldc 'Stub!'
    //   9: invokespecial <init> : (Ljava/lang/String;)V
    //   12: aload_1
    //   13: athrow
    //   14: astore_1
    //   15: aload_0
    //   16: monitorexit
    //   17: aload_1
    //   18: athrow
    // Exception table:
    //   from	to	target	type
    //   2	14	14	finally
  }
  
  public void removeRequestInterceptorByClass(Class<? extends HttpRequestInterceptor> paramClass) {
    throw new RuntimeException("Stub!");
  }
  
  public void removeResponseInterceptorByClass(Class<? extends HttpResponseInterceptor> paramClass) {
    throw new RuntimeException("Stub!");
  }
  
  public void setAuthSchemes(AuthSchemeRegistry paramAuthSchemeRegistry) {
    // Byte code:
    //   0: aload_0
    //   1: monitorenter
    //   2: new java/lang/RuntimeException
    //   5: astore_1
    //   6: aload_1
    //   7: ldc 'Stub!'
    //   9: invokespecial <init> : (Ljava/lang/String;)V
    //   12: aload_1
    //   13: athrow
    //   14: astore_1
    //   15: aload_0
    //   16: monitorexit
    //   17: aload_1
    //   18: athrow
    // Exception table:
    //   from	to	target	type
    //   2	14	14	finally
  }
  
  public void setCookieSpecs(CookieSpecRegistry paramCookieSpecRegistry) {
    // Byte code:
    //   0: aload_0
    //   1: monitorenter
    //   2: new java/lang/RuntimeException
    //   5: astore_1
    //   6: aload_1
    //   7: ldc 'Stub!'
    //   9: invokespecial <init> : (Ljava/lang/String;)V
    //   12: aload_1
    //   13: athrow
    //   14: astore_1
    //   15: aload_0
    //   16: monitorexit
    //   17: aload_1
    //   18: athrow
    // Exception table:
    //   from	to	target	type
    //   2	14	14	finally
  }
  
  public void setCookieStore(CookieStore paramCookieStore) {
    // Byte code:
    //   0: aload_0
    //   1: monitorenter
    //   2: new java/lang/RuntimeException
    //   5: astore_1
    //   6: aload_1
    //   7: ldc 'Stub!'
    //   9: invokespecial <init> : (Ljava/lang/String;)V
    //   12: aload_1
    //   13: athrow
    //   14: astore_1
    //   15: aload_0
    //   16: monitorexit
    //   17: aload_1
    //   18: athrow
    // Exception table:
    //   from	to	target	type
    //   2	14	14	finally
  }
  
  public void setCredentialsProvider(CredentialsProvider paramCredentialsProvider) {
    // Byte code:
    //   0: aload_0
    //   1: monitorenter
    //   2: new java/lang/RuntimeException
    //   5: astore_1
    //   6: aload_1
    //   7: ldc 'Stub!'
    //   9: invokespecial <init> : (Ljava/lang/String;)V
    //   12: aload_1
    //   13: athrow
    //   14: astore_1
    //   15: aload_0
    //   16: monitorexit
    //   17: aload_1
    //   18: athrow
    // Exception table:
    //   from	to	target	type
    //   2	14	14	finally
  }
  
  public void setHttpRequestRetryHandler(HttpRequestRetryHandler paramHttpRequestRetryHandler) {
    // Byte code:
    //   0: aload_0
    //   1: monitorenter
    //   2: new java/lang/RuntimeException
    //   5: astore_1
    //   6: aload_1
    //   7: ldc 'Stub!'
    //   9: invokespecial <init> : (Ljava/lang/String;)V
    //   12: aload_1
    //   13: athrow
    //   14: astore_1
    //   15: aload_0
    //   16: monitorexit
    //   17: aload_1
    //   18: athrow
    // Exception table:
    //   from	to	target	type
    //   2	14	14	finally
  }
  
  public void setKeepAliveStrategy(ConnectionKeepAliveStrategy paramConnectionKeepAliveStrategy) {
    // Byte code:
    //   0: aload_0
    //   1: monitorenter
    //   2: new java/lang/RuntimeException
    //   5: astore_1
    //   6: aload_1
    //   7: ldc 'Stub!'
    //   9: invokespecial <init> : (Ljava/lang/String;)V
    //   12: aload_1
    //   13: athrow
    //   14: astore_1
    //   15: aload_0
    //   16: monitorexit
    //   17: aload_1
    //   18: athrow
    // Exception table:
    //   from	to	target	type
    //   2	14	14	finally
  }
  
  public void setParams(HttpParams paramHttpParams) {
    // Byte code:
    //   0: aload_0
    //   1: monitorenter
    //   2: new java/lang/RuntimeException
    //   5: astore_1
    //   6: aload_1
    //   7: ldc 'Stub!'
    //   9: invokespecial <init> : (Ljava/lang/String;)V
    //   12: aload_1
    //   13: athrow
    //   14: astore_1
    //   15: aload_0
    //   16: monitorexit
    //   17: aload_1
    //   18: athrow
    // Exception table:
    //   from	to	target	type
    //   2	14	14	finally
  }
  
  public void setProxyAuthenticationHandler(AuthenticationHandler paramAuthenticationHandler) {
    // Byte code:
    //   0: aload_0
    //   1: monitorenter
    //   2: new java/lang/RuntimeException
    //   5: astore_1
    //   6: aload_1
    //   7: ldc 'Stub!'
    //   9: invokespecial <init> : (Ljava/lang/String;)V
    //   12: aload_1
    //   13: athrow
    //   14: astore_1
    //   15: aload_0
    //   16: monitorexit
    //   17: aload_1
    //   18: athrow
    // Exception table:
    //   from	to	target	type
    //   2	14	14	finally
  }
  
  public void setRedirectHandler(RedirectHandler paramRedirectHandler) {
    // Byte code:
    //   0: aload_0
    //   1: monitorenter
    //   2: new java/lang/RuntimeException
    //   5: astore_1
    //   6: aload_1
    //   7: ldc 'Stub!'
    //   9: invokespecial <init> : (Ljava/lang/String;)V
    //   12: aload_1
    //   13: athrow
    //   14: astore_1
    //   15: aload_0
    //   16: monitorexit
    //   17: aload_1
    //   18: athrow
    // Exception table:
    //   from	to	target	type
    //   2	14	14	finally
  }
  
  public void setReuseStrategy(ConnectionReuseStrategy paramConnectionReuseStrategy) {
    // Byte code:
    //   0: aload_0
    //   1: monitorenter
    //   2: new java/lang/RuntimeException
    //   5: astore_1
    //   6: aload_1
    //   7: ldc 'Stub!'
    //   9: invokespecial <init> : (Ljava/lang/String;)V
    //   12: aload_1
    //   13: athrow
    //   14: astore_1
    //   15: aload_0
    //   16: monitorexit
    //   17: aload_1
    //   18: athrow
    // Exception table:
    //   from	to	target	type
    //   2	14	14	finally
  }
  
  public void setRoutePlanner(HttpRoutePlanner paramHttpRoutePlanner) {
    // Byte code:
    //   0: aload_0
    //   1: monitorenter
    //   2: new java/lang/RuntimeException
    //   5: astore_1
    //   6: aload_1
    //   7: ldc 'Stub!'
    //   9: invokespecial <init> : (Ljava/lang/String;)V
    //   12: aload_1
    //   13: athrow
    //   14: astore_1
    //   15: aload_0
    //   16: monitorexit
    //   17: aload_1
    //   18: athrow
    // Exception table:
    //   from	to	target	type
    //   2	14	14	finally
  }
  
  public void setTargetAuthenticationHandler(AuthenticationHandler paramAuthenticationHandler) {
    // Byte code:
    //   0: aload_0
    //   1: monitorenter
    //   2: new java/lang/RuntimeException
    //   5: astore_1
    //   6: aload_1
    //   7: ldc 'Stub!'
    //   9: invokespecial <init> : (Ljava/lang/String;)V
    //   12: aload_1
    //   13: athrow
    //   14: astore_1
    //   15: aload_0
    //   16: monitorexit
    //   17: aload_1
    //   18: athrow
    // Exception table:
    //   from	to	target	type
    //   2	14	14	finally
  }
  
  public void setUserTokenHandler(UserTokenHandler paramUserTokenHandler) {
    // Byte code:
    //   0: aload_0
    //   1: monitorenter
    //   2: new java/lang/RuntimeException
    //   5: astore_1
    //   6: aload_1
    //   7: ldc 'Stub!'
    //   9: invokespecial <init> : (Ljava/lang/String;)V
    //   12: aload_1
    //   13: athrow
    //   14: astore_1
    //   15: aload_0
    //   16: monitorexit
    //   17: aload_1
    //   18: athrow
    // Exception table:
    //   from	to	target	type
    //   2	14	14	finally
  }
}


/* Location:              D:\Code\Crack\dex-tools-2.1-20190905-lanchon\zspns-pcgw-P36417A-0429-dex2jar.jar!\org\apache\http\impl\client\AbstractHttpClient.class
 * Java compiler version: 6 (50.0)
 * JD-Core Version:       1.1.3
 */