package com.tencent.wxop.stat;

import android.content.ContentValues;
import android.content.Context;
import android.database.Cursor;
import android.database.DatabaseUtils;
import android.database.sqlite.SQLiteDatabase;
import com.tencent.wxop.stat.a.d;
import com.tencent.wxop.stat.b.b;
import com.tencent.wxop.stat.b.c;
import com.tencent.wxop.stat.b.f;
import com.tencent.wxop.stat.b.l;
import java.util.HashMap;
import java.util.Iterator;
import java.util.List;
import java.util.concurrent.ConcurrentHashMap;

public class t {
  private static b bZ = l.av();
  
  private static Context ca = null;
  
  private static t cb = null;
  
  volatile int aI = 0;
  
  private String ab = "";
  
  private ac bW = null;
  
  private ac bX = null;
  
  c bY = null;
  
  private f be = null;
  
  private String bq = "";
  
  private int cc = 0;
  
  private ConcurrentHashMap<d, String> cd = null;
  
  private boolean ce = false;
  
  private HashMap<String, String> cf = new HashMap<String, String>();
  
  private t(Context paramContext) {
    try {
      f f1 = new f();
      this();
      this.be = f1;
      ca = paramContext.getApplicationContext();
      ConcurrentHashMap<Object, Object> concurrentHashMap = new ConcurrentHashMap<Object, Object>();
      this();
      this.cd = (ConcurrentHashMap)concurrentHashMap;
      this.ab = l.J(paramContext);
      StringBuilder stringBuilder = new StringBuilder();
      this("pri_");
      this.bq = stringBuilder.append(l.J(paramContext)).toString();
      ac ac1 = new ac();
      this(ca, this.ab);
      this.bW = ac1;
      ac1 = new ac();
      this(ca, this.bq);
      this.bX = ac1;
      b(true);
      b(false);
      aj();
      t(ca);
      I();
      an();
    } catch (Throwable throwable) {
      bZ.b(throwable);
    } 
  }
  
  private void I() {
    // Byte code:
    //   0: aload_0
    //   1: getfield bW : Lcom/tencent/wxop/stat/ac;
    //   4: invokevirtual getReadableDatabase : ()Landroid/database/sqlite/SQLiteDatabase;
    //   7: ldc 'config'
    //   9: aconst_null
    //   10: aconst_null
    //   11: aconst_null
    //   12: aconst_null
    //   13: aconst_null
    //   14: aconst_null
    //   15: invokevirtual query : (Ljava/lang/String;[Ljava/lang/String;Ljava/lang/String;[Ljava/lang/String;Ljava/lang/String;Ljava/lang/String;Ljava/lang/String;)Landroid/database/Cursor;
    //   18: astore_1
    //   19: aload_1
    //   20: astore_2
    //   21: aload_1
    //   22: invokeinterface moveToNext : ()Z
    //   27: ifeq -> 175
    //   30: aload_1
    //   31: astore_2
    //   32: aload_1
    //   33: iconst_0
    //   34: invokeinterface getInt : (I)I
    //   39: istore_3
    //   40: aload_1
    //   41: astore_2
    //   42: aload_1
    //   43: iconst_1
    //   44: invokeinterface getString : (I)Ljava/lang/String;
    //   49: astore #4
    //   51: aload_1
    //   52: astore_2
    //   53: aload_1
    //   54: iconst_2
    //   55: invokeinterface getString : (I)Ljava/lang/String;
    //   60: astore #5
    //   62: aload_1
    //   63: astore_2
    //   64: aload_1
    //   65: iconst_3
    //   66: invokeinterface getInt : (I)I
    //   71: istore #6
    //   73: aload_1
    //   74: astore_2
    //   75: new com/tencent/wxop/stat/ah
    //   78: astore #7
    //   80: aload_1
    //   81: astore_2
    //   82: aload #7
    //   84: iload_3
    //   85: invokespecial <init> : (I)V
    //   88: aload_1
    //   89: astore_2
    //   90: aload #7
    //   92: iload_3
    //   93: putfield aI : I
    //   96: aload_1
    //   97: astore_2
    //   98: new org/json/JSONObject
    //   101: astore #8
    //   103: aload_1
    //   104: astore_2
    //   105: aload #8
    //   107: aload #4
    //   109: invokespecial <init> : (Ljava/lang/String;)V
    //   112: aload_1
    //   113: astore_2
    //   114: aload #7
    //   116: aload #8
    //   118: putfield df : Lorg/json/JSONObject;
    //   121: aload_1
    //   122: astore_2
    //   123: aload #7
    //   125: aload #5
    //   127: putfield c : Ljava/lang/String;
    //   130: aload_1
    //   131: astore_2
    //   132: aload #7
    //   134: iload #6
    //   136: putfield L : I
    //   139: aload_1
    //   140: astore_2
    //   141: getstatic com/tencent/wxop/stat/t.ca : Landroid/content/Context;
    //   144: aload #7
    //   146: invokestatic a : (Landroid/content/Context;Lcom/tencent/wxop/stat/ah;)V
    //   149: goto -> 19
    //   152: astore #8
    //   154: aload_1
    //   155: astore_2
    //   156: getstatic com/tencent/wxop/stat/t.bZ : Lcom/tencent/wxop/stat/b/b;
    //   159: aload #8
    //   161: invokevirtual b : (Ljava/lang/Throwable;)V
    //   164: aload_1
    //   165: ifnull -> 174
    //   168: aload_1
    //   169: invokeinterface close : ()V
    //   174: return
    //   175: aload_1
    //   176: ifnull -> 174
    //   179: aload_1
    //   180: invokeinterface close : ()V
    //   185: goto -> 174
    //   188: astore_2
    //   189: aconst_null
    //   190: astore #8
    //   192: aload_2
    //   193: astore_1
    //   194: aload #8
    //   196: ifnull -> 206
    //   199: aload #8
    //   201: invokeinterface close : ()V
    //   206: aload_1
    //   207: athrow
    //   208: astore_1
    //   209: aload_2
    //   210: astore #8
    //   212: goto -> 194
    //   215: astore #8
    //   217: aconst_null
    //   218: astore_1
    //   219: goto -> 154
    // Exception table:
    //   from	to	target	type
    //   0	19	215	java/lang/Throwable
    //   0	19	188	finally
    //   21	30	152	java/lang/Throwable
    //   21	30	208	finally
    //   32	40	152	java/lang/Throwable
    //   32	40	208	finally
    //   42	51	152	java/lang/Throwable
    //   42	51	208	finally
    //   53	62	152	java/lang/Throwable
    //   53	62	208	finally
    //   64	73	152	java/lang/Throwable
    //   64	73	208	finally
    //   75	80	152	java/lang/Throwable
    //   75	80	208	finally
    //   82	88	152	java/lang/Throwable
    //   82	88	208	finally
    //   90	96	152	java/lang/Throwable
    //   90	96	208	finally
    //   98	103	152	java/lang/Throwable
    //   98	103	208	finally
    //   105	112	152	java/lang/Throwable
    //   105	112	208	finally
    //   114	121	152	java/lang/Throwable
    //   114	121	208	finally
    //   123	130	152	java/lang/Throwable
    //   123	130	208	finally
    //   132	139	152	java/lang/Throwable
    //   132	139	208	finally
    //   141	149	152	java/lang/Throwable
    //   141	149	208	finally
    //   156	164	208	finally
  }
  
  private void a(int paramInt, boolean paramBoolean) {
    // Byte code:
    //   0: aload_0
    //   1: monitorenter
    //   2: aload_0
    //   3: getfield aI : I
    //   6: ifle -> 21
    //   9: iload_1
    //   10: ifle -> 21
    //   13: invokestatic a : ()Z
    //   16: istore_3
    //   17: iload_3
    //   18: ifeq -> 24
    //   21: aload_0
    //   22: monitorexit
    //   23: return
    //   24: invokestatic k : ()Z
    //   27: ifeq -> 69
    //   30: getstatic com/tencent/wxop/stat/t.bZ : Lcom/tencent/wxop/stat/b/b;
    //   33: astore #4
    //   35: new java/lang/StringBuilder
    //   38: astore #5
    //   40: aload #5
    //   42: ldc 'Load '
    //   44: invokespecial <init> : (Ljava/lang/String;)V
    //   47: aload #4
    //   49: aload #5
    //   51: aload_0
    //   52: getfield aI : I
    //   55: invokevirtual append : (I)Ljava/lang/StringBuilder;
    //   58: ldc ' unsent events'
    //   60: invokevirtual append : (Ljava/lang/String;)Ljava/lang/StringBuilder;
    //   63: invokevirtual toString : ()Ljava/lang/String;
    //   66: invokevirtual b : (Ljava/lang/Object;)V
    //   69: new java/util/ArrayList
    //   72: astore #4
    //   74: aload #4
    //   76: iload_1
    //   77: invokespecial <init> : (I)V
    //   80: aload_0
    //   81: aload #4
    //   83: iload_1
    //   84: iload_2
    //   85: invokespecial b : (Ljava/util/List;IZ)V
    //   88: aload #4
    //   90: invokeinterface size : ()I
    //   95: ifle -> 21
    //   98: invokestatic k : ()Z
    //   101: ifeq -> 146
    //   104: getstatic com/tencent/wxop/stat/t.bZ : Lcom/tencent/wxop/stat/b/b;
    //   107: astore #6
    //   109: new java/lang/StringBuilder
    //   112: astore #5
    //   114: aload #5
    //   116: ldc 'Peek '
    //   118: invokespecial <init> : (Ljava/lang/String;)V
    //   121: aload #6
    //   123: aload #5
    //   125: aload #4
    //   127: invokeinterface size : ()I
    //   132: invokevirtual append : (I)Ljava/lang/StringBuilder;
    //   135: ldc ' unsent events.'
    //   137: invokevirtual append : (Ljava/lang/String;)Ljava/lang/StringBuilder;
    //   140: invokevirtual toString : ()Ljava/lang/String;
    //   143: invokevirtual b : (Ljava/lang/Object;)V
    //   146: aload_0
    //   147: aload #4
    //   149: iconst_2
    //   150: iload_2
    //   151: invokespecial a : (Ljava/util/List;IZ)V
    //   154: getstatic com/tencent/wxop/stat/t.ca : Landroid/content/Context;
    //   157: invokestatic Z : (Landroid/content/Context;)Lcom/tencent/wxop/stat/ak;
    //   160: astore #5
    //   162: new com/tencent/wxop/stat/aa
    //   165: astore #6
    //   167: aload #6
    //   169: aload_0
    //   170: aload #4
    //   172: iload_2
    //   173: invokespecial <init> : (Lcom/tencent/wxop/stat/t;Ljava/util/List;Z)V
    //   176: aload #5
    //   178: aload #4
    //   180: aload #6
    //   182: invokevirtual b : (Ljava/util/List;Lcom/tencent/wxop/stat/aj;)V
    //   185: goto -> 21
    //   188: astore #4
    //   190: getstatic com/tencent/wxop/stat/t.bZ : Lcom/tencent/wxop/stat/b/b;
    //   193: aload #4
    //   195: invokevirtual b : (Ljava/lang/Throwable;)V
    //   198: goto -> 21
    //   201: astore #4
    //   203: aload_0
    //   204: monitorexit
    //   205: aload #4
    //   207: athrow
    // Exception table:
    //   from	to	target	type
    //   2	9	188	java/lang/Throwable
    //   2	9	201	finally
    //   13	17	188	java/lang/Throwable
    //   13	17	201	finally
    //   24	69	188	java/lang/Throwable
    //   24	69	201	finally
    //   69	146	188	java/lang/Throwable
    //   69	146	201	finally
    //   146	185	188	java/lang/Throwable
    //   146	185	201	finally
    //   190	198	201	finally
  }
  
  private void a(d paramd, aj paramaj, boolean paramBoolean1, boolean paramBoolean2) {
    // Byte code:
    //   0: aconst_null
    //   1: astore #5
    //   3: aconst_null
    //   4: astore #6
    //   6: aload_0
    //   7: monitorenter
    //   8: invokestatic s : ()I
    //   11: ifle -> 443
    //   14: getstatic com/tencent/wxop/stat/c.ay : I
    //   17: istore #7
    //   19: iload #7
    //   21: ifle -> 33
    //   24: iload_3
    //   25: ifne -> 33
    //   28: iload #4
    //   30: ifeq -> 579
    //   33: aload_0
    //   34: iload_3
    //   35: invokespecial c : (Z)Landroid/database/sqlite/SQLiteDatabase;
    //   38: astore #8
    //   40: aload #8
    //   42: astore #6
    //   44: aload #8
    //   46: astore #5
    //   48: aload #8
    //   50: invokevirtual beginTransaction : ()V
    //   53: iload_3
    //   54: ifne -> 125
    //   57: aload #8
    //   59: astore #6
    //   61: aload #8
    //   63: astore #5
    //   65: aload_0
    //   66: getfield aI : I
    //   69: invokestatic s : ()I
    //   72: if_icmple -> 125
    //   75: aload #8
    //   77: astore #6
    //   79: aload #8
    //   81: astore #5
    //   83: getstatic com/tencent/wxop/stat/t.bZ : Lcom/tencent/wxop/stat/b/b;
    //   86: ldc 'Too many events stored in db.'
    //   88: invokevirtual warn : (Ljava/lang/Object;)V
    //   91: aload #8
    //   93: astore #6
    //   95: aload #8
    //   97: astore #5
    //   99: aload_0
    //   100: aload_0
    //   101: getfield aI : I
    //   104: aload_0
    //   105: getfield bW : Lcom/tencent/wxop/stat/ac;
    //   108: invokevirtual getWritableDatabase : ()Landroid/database/sqlite/SQLiteDatabase;
    //   111: ldc_w 'events'
    //   114: ldc_w 'event_id in (select event_id from events where timestamp in (select min(timestamp) from events) limit 1)'
    //   117: aconst_null
    //   118: invokevirtual delete : (Ljava/lang/String;Ljava/lang/String;[Ljava/lang/String;)I
    //   121: isub
    //   122: putfield aI : I
    //   125: aload #8
    //   127: astore #6
    //   129: aload #8
    //   131: astore #5
    //   133: new android/content/ContentValues
    //   136: astore #9
    //   138: aload #8
    //   140: astore #6
    //   142: aload #8
    //   144: astore #5
    //   146: aload #9
    //   148: invokespecial <init> : ()V
    //   151: aload #8
    //   153: astore #6
    //   155: aload #8
    //   157: astore #5
    //   159: aload_1
    //   160: invokevirtual af : ()Ljava/lang/String;
    //   163: astore #10
    //   165: aload #8
    //   167: astore #6
    //   169: aload #8
    //   171: astore #5
    //   173: invokestatic k : ()Z
    //   176: ifeq -> 244
    //   179: aload #8
    //   181: astore #6
    //   183: aload #8
    //   185: astore #5
    //   187: getstatic com/tencent/wxop/stat/t.bZ : Lcom/tencent/wxop/stat/b/b;
    //   190: astore #11
    //   192: aload #8
    //   194: astore #6
    //   196: aload #8
    //   198: astore #5
    //   200: new java/lang/StringBuilder
    //   203: astore #12
    //   205: aload #8
    //   207: astore #6
    //   209: aload #8
    //   211: astore #5
    //   213: aload #12
    //   215: ldc_w 'insert 1 event, content:'
    //   218: invokespecial <init> : (Ljava/lang/String;)V
    //   221: aload #8
    //   223: astore #6
    //   225: aload #8
    //   227: astore #5
    //   229: aload #11
    //   231: aload #12
    //   233: aload #10
    //   235: invokevirtual append : (Ljava/lang/String;)Ljava/lang/StringBuilder;
    //   238: invokevirtual toString : ()Ljava/lang/String;
    //   241: invokevirtual b : (Ljava/lang/Object;)V
    //   244: aload #8
    //   246: astore #6
    //   248: aload #8
    //   250: astore #5
    //   252: aload #9
    //   254: ldc_w 'content'
    //   257: aload #10
    //   259: invokestatic q : (Ljava/lang/String;)Ljava/lang/String;
    //   262: invokevirtual put : (Ljava/lang/String;Ljava/lang/String;)V
    //   265: aload #8
    //   267: astore #6
    //   269: aload #8
    //   271: astore #5
    //   273: aload #9
    //   275: ldc_w 'send_count'
    //   278: ldc_w '0'
    //   281: invokevirtual put : (Ljava/lang/String;Ljava/lang/String;)V
    //   284: aload #8
    //   286: astore #6
    //   288: aload #8
    //   290: astore #5
    //   292: aload #9
    //   294: ldc_w 'status'
    //   297: iconst_1
    //   298: invokestatic toString : (I)Ljava/lang/String;
    //   301: invokevirtual put : (Ljava/lang/String;Ljava/lang/String;)V
    //   304: aload #8
    //   306: astore #6
    //   308: aload #8
    //   310: astore #5
    //   312: aload #9
    //   314: ldc_w 'timestamp'
    //   317: aload_1
    //   318: invokevirtual ad : ()J
    //   321: invokestatic valueOf : (J)Ljava/lang/Long;
    //   324: invokevirtual put : (Ljava/lang/String;Ljava/lang/Long;)V
    //   327: aload #8
    //   329: astore #6
    //   331: aload #8
    //   333: astore #5
    //   335: aload #8
    //   337: ldc_w 'events'
    //   340: aconst_null
    //   341: aload #9
    //   343: invokevirtual insert : (Ljava/lang/String;Ljava/lang/String;Landroid/content/ContentValues;)J
    //   346: lstore #13
    //   348: aload #8
    //   350: astore #6
    //   352: aload #8
    //   354: astore #5
    //   356: aload #8
    //   358: invokevirtual setTransactionSuccessful : ()V
    //   361: lload #13
    //   363: lstore #15
    //   365: aload #8
    //   367: ifnull -> 744
    //   370: aload #8
    //   372: invokevirtual endTransaction : ()V
    //   375: lload #13
    //   377: lconst_0
    //   378: lcmp
    //   379: ifle -> 543
    //   382: aload_0
    //   383: aload_0
    //   384: getfield aI : I
    //   387: iconst_1
    //   388: iadd
    //   389: putfield aI : I
    //   392: invokestatic k : ()Z
    //   395: ifeq -> 433
    //   398: getstatic com/tencent/wxop/stat/t.bZ : Lcom/tencent/wxop/stat/b/b;
    //   401: astore #5
    //   403: new java/lang/StringBuilder
    //   406: astore #6
    //   408: aload #6
    //   410: ldc_w 'directStoreEvent insert event to db, event:'
    //   413: invokespecial <init> : (Ljava/lang/String;)V
    //   416: aload #5
    //   418: aload #6
    //   420: aload_1
    //   421: invokevirtual af : ()Ljava/lang/String;
    //   424: invokevirtual append : (Ljava/lang/String;)Ljava/lang/StringBuilder;
    //   427: invokevirtual toString : ()Ljava/lang/String;
    //   430: invokevirtual e : (Ljava/lang/Object;)V
    //   433: aload_2
    //   434: ifnull -> 443
    //   437: aload_2
    //   438: invokeinterface ah : ()V
    //   443: aload_0
    //   444: monitorexit
    //   445: return
    //   446: astore #6
    //   448: getstatic com/tencent/wxop/stat/t.bZ : Lcom/tencent/wxop/stat/b/b;
    //   451: aload #6
    //   453: invokevirtual b : (Ljava/lang/Throwable;)V
    //   456: goto -> 375
    //   459: astore #8
    //   461: ldc2_w -1
    //   464: lstore #15
    //   466: aload #6
    //   468: astore #5
    //   470: getstatic com/tencent/wxop/stat/t.bZ : Lcom/tencent/wxop/stat/b/b;
    //   473: aload #8
    //   475: invokevirtual b : (Ljava/lang/Throwable;)V
    //   478: aload #6
    //   480: ifnull -> 744
    //   483: aload #6
    //   485: invokevirtual endTransaction : ()V
    //   488: ldc2_w -1
    //   491: lstore #13
    //   493: goto -> 375
    //   496: astore #6
    //   498: getstatic com/tencent/wxop/stat/t.bZ : Lcom/tencent/wxop/stat/b/b;
    //   501: aload #6
    //   503: invokevirtual b : (Ljava/lang/Throwable;)V
    //   506: ldc2_w -1
    //   509: lstore #13
    //   511: goto -> 375
    //   514: astore_1
    //   515: aload #5
    //   517: ifnull -> 525
    //   520: aload #5
    //   522: invokevirtual endTransaction : ()V
    //   525: aload_1
    //   526: athrow
    //   527: astore_1
    //   528: aload_0
    //   529: monitorexit
    //   530: aload_1
    //   531: athrow
    //   532: astore_2
    //   533: getstatic com/tencent/wxop/stat/t.bZ : Lcom/tencent/wxop/stat/b/b;
    //   536: aload_2
    //   537: invokevirtual b : (Ljava/lang/Throwable;)V
    //   540: goto -> 525
    //   543: getstatic com/tencent/wxop/stat/t.bZ : Lcom/tencent/wxop/stat/b/b;
    //   546: astore_2
    //   547: new java/lang/StringBuilder
    //   550: astore #6
    //   552: aload #6
    //   554: ldc_w 'Failed to store event:'
    //   557: invokespecial <init> : (Ljava/lang/String;)V
    //   560: aload_2
    //   561: aload #6
    //   563: aload_1
    //   564: invokevirtual af : ()Ljava/lang/String;
    //   567: invokevirtual append : (Ljava/lang/String;)Ljava/lang/StringBuilder;
    //   570: invokevirtual toString : ()Ljava/lang/String;
    //   573: invokevirtual error : (Ljava/lang/Object;)V
    //   576: goto -> 443
    //   579: getstatic com/tencent/wxop/stat/c.ay : I
    //   582: ifle -> 443
    //   585: invokestatic k : ()Z
    //   588: ifeq -> 689
    //   591: getstatic com/tencent/wxop/stat/t.bZ : Lcom/tencent/wxop/stat/b/b;
    //   594: astore #6
    //   596: new java/lang/StringBuilder
    //   599: astore #5
    //   601: aload #5
    //   603: ldc_w 'cacheEventsInMemory.size():'
    //   606: invokespecial <init> : (Ljava/lang/String;)V
    //   609: aload #6
    //   611: aload #5
    //   613: aload_0
    //   614: getfield cd : Ljava/util/concurrent/ConcurrentHashMap;
    //   617: invokevirtual size : ()I
    //   620: invokevirtual append : (I)Ljava/lang/StringBuilder;
    //   623: ldc_w ',numEventsCachedInMemory:'
    //   626: invokevirtual append : (Ljava/lang/String;)Ljava/lang/StringBuilder;
    //   629: getstatic com/tencent/wxop/stat/c.ay : I
    //   632: invokevirtual append : (I)Ljava/lang/StringBuilder;
    //   635: ldc_w ',numStoredEvents:'
    //   638: invokevirtual append : (Ljava/lang/String;)Ljava/lang/StringBuilder;
    //   641: aload_0
    //   642: getfield aI : I
    //   645: invokevirtual append : (I)Ljava/lang/StringBuilder;
    //   648: invokevirtual toString : ()Ljava/lang/String;
    //   651: invokevirtual b : (Ljava/lang/Object;)V
    //   654: getstatic com/tencent/wxop/stat/t.bZ : Lcom/tencent/wxop/stat/b/b;
    //   657: astore #5
    //   659: new java/lang/StringBuilder
    //   662: astore #6
    //   664: aload #6
    //   666: ldc_w 'cache event:'
    //   669: invokespecial <init> : (Ljava/lang/String;)V
    //   672: aload #5
    //   674: aload #6
    //   676: aload_1
    //   677: invokevirtual af : ()Ljava/lang/String;
    //   680: invokevirtual append : (Ljava/lang/String;)Ljava/lang/StringBuilder;
    //   683: invokevirtual toString : ()Ljava/lang/String;
    //   686: invokevirtual b : (Ljava/lang/Object;)V
    //   689: aload_0
    //   690: getfield cd : Ljava/util/concurrent/ConcurrentHashMap;
    //   693: aload_1
    //   694: ldc ''
    //   696: invokevirtual put : (Ljava/lang/Object;Ljava/lang/Object;)Ljava/lang/Object;
    //   699: pop
    //   700: aload_0
    //   701: getfield cd : Ljava/util/concurrent/ConcurrentHashMap;
    //   704: invokevirtual size : ()I
    //   707: getstatic com/tencent/wxop/stat/c.ay : I
    //   710: if_icmplt -> 717
    //   713: aload_0
    //   714: invokespecial am : ()V
    //   717: aload_2
    //   718: ifnull -> 443
    //   721: aload_0
    //   722: getfield cd : Ljava/util/concurrent/ConcurrentHashMap;
    //   725: invokevirtual size : ()I
    //   728: ifle -> 735
    //   731: aload_0
    //   732: invokespecial am : ()V
    //   735: aload_2
    //   736: invokeinterface ah : ()V
    //   741: goto -> 443
    //   744: lload #15
    //   746: lstore #13
    //   748: goto -> 375
    // Exception table:
    //   from	to	target	type
    //   8	19	527	finally
    //   33	40	459	java/lang/Throwable
    //   33	40	514	finally
    //   48	53	459	java/lang/Throwable
    //   48	53	514	finally
    //   65	75	459	java/lang/Throwable
    //   65	75	514	finally
    //   83	91	459	java/lang/Throwable
    //   83	91	514	finally
    //   99	125	459	java/lang/Throwable
    //   99	125	514	finally
    //   133	138	459	java/lang/Throwable
    //   133	138	514	finally
    //   146	151	459	java/lang/Throwable
    //   146	151	514	finally
    //   159	165	459	java/lang/Throwable
    //   159	165	514	finally
    //   173	179	459	java/lang/Throwable
    //   173	179	514	finally
    //   187	192	459	java/lang/Throwable
    //   187	192	514	finally
    //   200	205	459	java/lang/Throwable
    //   200	205	514	finally
    //   213	221	459	java/lang/Throwable
    //   213	221	514	finally
    //   229	244	459	java/lang/Throwable
    //   229	244	514	finally
    //   252	265	459	java/lang/Throwable
    //   252	265	514	finally
    //   273	284	459	java/lang/Throwable
    //   273	284	514	finally
    //   292	304	459	java/lang/Throwable
    //   292	304	514	finally
    //   312	327	459	java/lang/Throwable
    //   312	327	514	finally
    //   335	348	459	java/lang/Throwable
    //   335	348	514	finally
    //   356	361	459	java/lang/Throwable
    //   356	361	514	finally
    //   370	375	446	java/lang/Throwable
    //   370	375	527	finally
    //   382	433	527	finally
    //   437	443	527	finally
    //   448	456	527	finally
    //   470	478	514	finally
    //   483	488	496	java/lang/Throwable
    //   483	488	527	finally
    //   498	506	527	finally
    //   520	525	532	java/lang/Throwable
    //   520	525	527	finally
    //   525	527	527	finally
    //   533	540	527	finally
    //   543	576	527	finally
    //   579	689	527	finally
    //   689	717	527	finally
    //   721	735	527	finally
    //   735	741	527	finally
  }
  
  private void a(ah paramah) {
    // Byte code:
    //   0: aload_0
    //   1: monitorenter
    //   2: aload_1
    //   3: getfield df : Lorg/json/JSONObject;
    //   6: invokevirtual toString : ()Ljava/lang/String;
    //   9: astore_2
    //   10: aload_2
    //   11: invokestatic t : (Ljava/lang/String;)Ljava/lang/String;
    //   14: astore_3
    //   15: new android/content/ContentValues
    //   18: astore #4
    //   20: aload #4
    //   22: invokespecial <init> : ()V
    //   25: aload #4
    //   27: ldc_w 'content'
    //   30: aload_1
    //   31: getfield df : Lorg/json/JSONObject;
    //   34: invokevirtual toString : ()Ljava/lang/String;
    //   37: invokevirtual put : (Ljava/lang/String;Ljava/lang/String;)V
    //   40: aload #4
    //   42: ldc_w 'md5sum'
    //   45: aload_3
    //   46: invokevirtual put : (Ljava/lang/String;Ljava/lang/String;)V
    //   49: aload_1
    //   50: aload_3
    //   51: putfield c : Ljava/lang/String;
    //   54: aload #4
    //   56: ldc_w 'version'
    //   59: aload_1
    //   60: getfield L : I
    //   63: invokestatic valueOf : (I)Ljava/lang/Integer;
    //   66: invokevirtual put : (Ljava/lang/String;Ljava/lang/Integer;)V
    //   69: aload_0
    //   70: getfield bW : Lcom/tencent/wxop/stat/ac;
    //   73: invokevirtual getReadableDatabase : ()Landroid/database/sqlite/SQLiteDatabase;
    //   76: ldc 'config'
    //   78: aconst_null
    //   79: aconst_null
    //   80: aconst_null
    //   81: aconst_null
    //   82: aconst_null
    //   83: aconst_null
    //   84: invokevirtual query : (Ljava/lang/String;[Ljava/lang/String;Ljava/lang/String;[Ljava/lang/String;Ljava/lang/String;Ljava/lang/String;Ljava/lang/String;)Landroid/database/Cursor;
    //   87: astore #5
    //   89: aload #5
    //   91: astore_3
    //   92: aload #5
    //   94: invokeinterface moveToNext : ()Z
    //   99: ifeq -> 442
    //   102: aload #5
    //   104: astore_3
    //   105: aload #5
    //   107: iconst_0
    //   108: invokeinterface getInt : (I)I
    //   113: aload_1
    //   114: getfield aI : I
    //   117: if_icmpne -> 89
    //   120: iconst_1
    //   121: istore #6
    //   123: aload #5
    //   125: astore_3
    //   126: aload_0
    //   127: getfield bW : Lcom/tencent/wxop/stat/ac;
    //   130: invokevirtual getWritableDatabase : ()Landroid/database/sqlite/SQLiteDatabase;
    //   133: invokevirtual beginTransaction : ()V
    //   136: iconst_1
    //   137: iload #6
    //   139: if_icmpne -> 268
    //   142: aload #5
    //   144: astore_3
    //   145: aload_0
    //   146: getfield bW : Lcom/tencent/wxop/stat/ac;
    //   149: invokevirtual getWritableDatabase : ()Landroid/database/sqlite/SQLiteDatabase;
    //   152: ldc 'config'
    //   154: aload #4
    //   156: ldc_w 'type=?'
    //   159: iconst_1
    //   160: anewarray java/lang/String
    //   163: dup
    //   164: iconst_0
    //   165: aload_1
    //   166: getfield aI : I
    //   169: invokestatic toString : (I)Ljava/lang/String;
    //   172: aastore
    //   173: invokevirtual update : (Ljava/lang/String;Landroid/content/ContentValues;Ljava/lang/String;[Ljava/lang/String;)I
    //   176: i2l
    //   177: lstore #7
    //   179: lload #7
    //   181: ldc2_w -1
    //   184: lcmp
    //   185: ifne -> 309
    //   188: aload #5
    //   190: astore_3
    //   191: getstatic com/tencent/wxop/stat/t.bZ : Lcom/tencent/wxop/stat/b/b;
    //   194: astore_1
    //   195: aload #5
    //   197: astore_3
    //   198: new java/lang/StringBuilder
    //   201: astore #4
    //   203: aload #5
    //   205: astore_3
    //   206: aload #4
    //   208: ldc_w 'Failed to store cfg:'
    //   211: invokespecial <init> : (Ljava/lang/String;)V
    //   214: aload #5
    //   216: astore_3
    //   217: aload_1
    //   218: aload #4
    //   220: aload_2
    //   221: invokevirtual append : (Ljava/lang/String;)Ljava/lang/StringBuilder;
    //   224: invokevirtual toString : ()Ljava/lang/String;
    //   227: invokevirtual d : (Ljava/lang/Object;)V
    //   230: aload #5
    //   232: astore_3
    //   233: aload_0
    //   234: getfield bW : Lcom/tencent/wxop/stat/ac;
    //   237: invokevirtual getWritableDatabase : ()Landroid/database/sqlite/SQLiteDatabase;
    //   240: invokevirtual setTransactionSuccessful : ()V
    //   243: aload #5
    //   245: ifnull -> 255
    //   248: aload #5
    //   250: invokeinterface close : ()V
    //   255: aload_0
    //   256: getfield bW : Lcom/tencent/wxop/stat/ac;
    //   259: invokevirtual getWritableDatabase : ()Landroid/database/sqlite/SQLiteDatabase;
    //   262: invokevirtual endTransaction : ()V
    //   265: aload_0
    //   266: monitorexit
    //   267: return
    //   268: aload #5
    //   270: astore_3
    //   271: aload #4
    //   273: ldc_w 'type'
    //   276: aload_1
    //   277: getfield aI : I
    //   280: invokestatic valueOf : (I)Ljava/lang/Integer;
    //   283: invokevirtual put : (Ljava/lang/String;Ljava/lang/Integer;)V
    //   286: aload #5
    //   288: astore_3
    //   289: aload_0
    //   290: getfield bW : Lcom/tencent/wxop/stat/ac;
    //   293: invokevirtual getWritableDatabase : ()Landroid/database/sqlite/SQLiteDatabase;
    //   296: ldc 'config'
    //   298: aconst_null
    //   299: aload #4
    //   301: invokevirtual insert : (Ljava/lang/String;Ljava/lang/String;Landroid/content/ContentValues;)J
    //   304: lstore #7
    //   306: goto -> 179
    //   309: aload #5
    //   311: astore_3
    //   312: getstatic com/tencent/wxop/stat/t.bZ : Lcom/tencent/wxop/stat/b/b;
    //   315: astore #4
    //   317: aload #5
    //   319: astore_3
    //   320: new java/lang/StringBuilder
    //   323: astore_1
    //   324: aload #5
    //   326: astore_3
    //   327: aload_1
    //   328: ldc_w 'Sucessed to store cfg:'
    //   331: invokespecial <init> : (Ljava/lang/String;)V
    //   334: aload #5
    //   336: astore_3
    //   337: aload #4
    //   339: aload_1
    //   340: aload_2
    //   341: invokevirtual append : (Ljava/lang/String;)Ljava/lang/StringBuilder;
    //   344: invokevirtual toString : ()Ljava/lang/String;
    //   347: invokevirtual e : (Ljava/lang/Object;)V
    //   350: goto -> 230
    //   353: astore_1
    //   354: aload #5
    //   356: astore_3
    //   357: getstatic com/tencent/wxop/stat/t.bZ : Lcom/tencent/wxop/stat/b/b;
    //   360: aload_1
    //   361: invokevirtual b : (Ljava/lang/Throwable;)V
    //   364: aload #5
    //   366: ifnull -> 376
    //   369: aload #5
    //   371: invokeinterface close : ()V
    //   376: aload_0
    //   377: getfield bW : Lcom/tencent/wxop/stat/ac;
    //   380: invokevirtual getWritableDatabase : ()Landroid/database/sqlite/SQLiteDatabase;
    //   383: invokevirtual endTransaction : ()V
    //   386: goto -> 265
    //   389: astore_1
    //   390: goto -> 265
    //   393: astore_1
    //   394: aconst_null
    //   395: astore_3
    //   396: aload_3
    //   397: ifnull -> 406
    //   400: aload_3
    //   401: invokeinterface close : ()V
    //   406: aload_0
    //   407: getfield bW : Lcom/tencent/wxop/stat/ac;
    //   410: invokevirtual getWritableDatabase : ()Landroid/database/sqlite/SQLiteDatabase;
    //   413: invokevirtual endTransaction : ()V
    //   416: aload_1
    //   417: athrow
    //   418: astore_1
    //   419: aload_0
    //   420: monitorexit
    //   421: aload_1
    //   422: athrow
    //   423: astore_3
    //   424: goto -> 416
    //   427: astore_1
    //   428: goto -> 396
    //   431: astore_1
    //   432: aconst_null
    //   433: astore #5
    //   435: goto -> 354
    //   438: astore_1
    //   439: goto -> 265
    //   442: iconst_0
    //   443: istore #6
    //   445: goto -> 123
    // Exception table:
    //   from	to	target	type
    //   2	89	431	java/lang/Throwable
    //   2	89	393	finally
    //   92	102	353	java/lang/Throwable
    //   92	102	427	finally
    //   105	120	353	java/lang/Throwable
    //   105	120	427	finally
    //   126	136	353	java/lang/Throwable
    //   126	136	427	finally
    //   145	179	353	java/lang/Throwable
    //   145	179	427	finally
    //   191	195	353	java/lang/Throwable
    //   191	195	427	finally
    //   198	203	353	java/lang/Throwable
    //   198	203	427	finally
    //   206	214	353	java/lang/Throwable
    //   206	214	427	finally
    //   217	230	353	java/lang/Throwable
    //   217	230	427	finally
    //   233	243	353	java/lang/Throwable
    //   233	243	427	finally
    //   248	255	418	finally
    //   255	265	438	java/lang/Exception
    //   255	265	418	finally
    //   271	286	353	java/lang/Throwable
    //   271	286	427	finally
    //   289	306	353	java/lang/Throwable
    //   289	306	427	finally
    //   312	317	353	java/lang/Throwable
    //   312	317	427	finally
    //   320	324	353	java/lang/Throwable
    //   320	324	427	finally
    //   327	334	353	java/lang/Throwable
    //   327	334	427	finally
    //   337	350	353	java/lang/Throwable
    //   337	350	427	finally
    //   357	364	427	finally
    //   369	376	418	finally
    //   376	386	389	java/lang/Exception
    //   376	386	418	finally
    //   400	406	418	finally
    //   406	416	423	java/lang/Exception
    //   406	416	418	finally
    //   416	418	418	finally
  }
  
  private void a(List<ad> paramList, int paramInt, boolean paramBoolean) {
    // Byte code:
    //   0: aconst_null
    //   1: astore #4
    //   3: aconst_null
    //   4: astore #5
    //   6: aload_0
    //   7: monitorenter
    //   8: aload_1
    //   9: invokeinterface size : ()I
    //   14: istore #6
    //   16: iload #6
    //   18: ifne -> 24
    //   21: aload_0
    //   22: monitorexit
    //   23: return
    //   24: iload_3
    //   25: ifne -> 288
    //   28: invokestatic p : ()I
    //   31: istore #6
    //   33: aload_0
    //   34: iload_3
    //   35: invokespecial c : (Z)Landroid/database/sqlite/SQLiteDatabase;
    //   38: astore #7
    //   40: iload_2
    //   41: iconst_2
    //   42: if_icmpne -> 296
    //   45: aload #7
    //   47: astore #8
    //   49: new java/lang/StringBuilder
    //   52: astore #4
    //   54: aload #7
    //   56: astore #8
    //   58: aload #4
    //   60: ldc_w 'update events set status='
    //   63: invokespecial <init> : (Ljava/lang/String;)V
    //   66: aload #7
    //   68: astore #8
    //   70: aload #4
    //   72: iload_2
    //   73: invokevirtual append : (I)Ljava/lang/StringBuilder;
    //   76: ldc_w ', send_count=send_count+1  where '
    //   79: invokevirtual append : (Ljava/lang/String;)Ljava/lang/StringBuilder;
    //   82: aload_1
    //   83: invokestatic b : (Ljava/util/List;)Ljava/lang/String;
    //   86: invokevirtual append : (Ljava/lang/String;)Ljava/lang/StringBuilder;
    //   89: invokevirtual toString : ()Ljava/lang/String;
    //   92: astore #4
    //   94: aload #5
    //   96: astore_1
    //   97: aload #4
    //   99: astore #5
    //   101: aload #7
    //   103: astore #8
    //   105: invokestatic k : ()Z
    //   108: ifeq -> 160
    //   111: aload #7
    //   113: astore #8
    //   115: getstatic com/tencent/wxop/stat/t.bZ : Lcom/tencent/wxop/stat/b/b;
    //   118: astore #4
    //   120: aload #7
    //   122: astore #8
    //   124: new java/lang/StringBuilder
    //   127: astore #9
    //   129: aload #7
    //   131: astore #8
    //   133: aload #9
    //   135: ldc_w 'update sql:'
    //   138: invokespecial <init> : (Ljava/lang/String;)V
    //   141: aload #7
    //   143: astore #8
    //   145: aload #4
    //   147: aload #9
    //   149: aload #5
    //   151: invokevirtual append : (Ljava/lang/String;)Ljava/lang/StringBuilder;
    //   154: invokevirtual toString : ()Ljava/lang/String;
    //   157: invokevirtual b : (Ljava/lang/Object;)V
    //   160: aload #7
    //   162: astore #8
    //   164: aload #7
    //   166: invokevirtual beginTransaction : ()V
    //   169: aload #7
    //   171: astore #8
    //   173: aload #7
    //   175: aload #5
    //   177: invokevirtual execSQL : (Ljava/lang/String;)V
    //   180: aload_1
    //   181: ifnull -> 250
    //   184: aload #7
    //   186: astore #8
    //   188: getstatic com/tencent/wxop/stat/t.bZ : Lcom/tencent/wxop/stat/b/b;
    //   191: astore #5
    //   193: aload #7
    //   195: astore #8
    //   197: new java/lang/StringBuilder
    //   200: astore #4
    //   202: aload #7
    //   204: astore #8
    //   206: aload #4
    //   208: ldc_w 'update for delete sql:'
    //   211: invokespecial <init> : (Ljava/lang/String;)V
    //   214: aload #7
    //   216: astore #8
    //   218: aload #5
    //   220: aload #4
    //   222: aload_1
    //   223: invokevirtual append : (Ljava/lang/String;)Ljava/lang/StringBuilder;
    //   226: invokevirtual toString : ()Ljava/lang/String;
    //   229: invokevirtual b : (Ljava/lang/Object;)V
    //   232: aload #7
    //   234: astore #8
    //   236: aload #7
    //   238: aload_1
    //   239: invokevirtual execSQL : (Ljava/lang/String;)V
    //   242: aload #7
    //   244: astore #8
    //   246: aload_0
    //   247: invokespecial aj : ()V
    //   250: aload #7
    //   252: astore #8
    //   254: aload #7
    //   256: invokevirtual setTransactionSuccessful : ()V
    //   259: aload #7
    //   261: ifnull -> 21
    //   264: aload #7
    //   266: invokevirtual endTransaction : ()V
    //   269: goto -> 21
    //   272: astore_1
    //   273: getstatic com/tencent/wxop/stat/t.bZ : Lcom/tencent/wxop/stat/b/b;
    //   276: aload_1
    //   277: invokevirtual b : (Ljava/lang/Throwable;)V
    //   280: goto -> 21
    //   283: astore_1
    //   284: aload_0
    //   285: monitorexit
    //   286: aload_1
    //   287: athrow
    //   288: invokestatic n : ()I
    //   291: istore #6
    //   293: goto -> 33
    //   296: aload #7
    //   298: astore #8
    //   300: new java/lang/StringBuilder
    //   303: astore #5
    //   305: aload #7
    //   307: astore #8
    //   309: aload #5
    //   311: ldc_w 'update events set status='
    //   314: invokespecial <init> : (Ljava/lang/String;)V
    //   317: aload #7
    //   319: astore #8
    //   321: aload #5
    //   323: iload_2
    //   324: invokevirtual append : (I)Ljava/lang/StringBuilder;
    //   327: ldc_w ' where '
    //   330: invokevirtual append : (Ljava/lang/String;)Ljava/lang/StringBuilder;
    //   333: aload_1
    //   334: invokestatic b : (Ljava/util/List;)Ljava/lang/String;
    //   337: invokevirtual append : (Ljava/lang/String;)Ljava/lang/StringBuilder;
    //   340: invokevirtual toString : ()Ljava/lang/String;
    //   343: astore #5
    //   345: aload #4
    //   347: astore_1
    //   348: aload #7
    //   350: astore #8
    //   352: aload_0
    //   353: getfield cc : I
    //   356: iconst_3
    //   357: irem
    //   358: ifne -> 394
    //   361: aload #7
    //   363: astore #8
    //   365: new java/lang/StringBuilder
    //   368: astore_1
    //   369: aload #7
    //   371: astore #8
    //   373: aload_1
    //   374: ldc_w 'delete from events where send_count>'
    //   377: invokespecial <init> : (Ljava/lang/String;)V
    //   380: aload #7
    //   382: astore #8
    //   384: aload_1
    //   385: iload #6
    //   387: invokevirtual append : (I)Ljava/lang/StringBuilder;
    //   390: invokevirtual toString : ()Ljava/lang/String;
    //   393: astore_1
    //   394: aload #7
    //   396: astore #8
    //   398: aload_0
    //   399: aload_0
    //   400: getfield cc : I
    //   403: iconst_1
    //   404: iadd
    //   405: putfield cc : I
    //   408: goto -> 101
    //   411: astore_1
    //   412: aconst_null
    //   413: astore #7
    //   415: aload #7
    //   417: astore #8
    //   419: getstatic com/tencent/wxop/stat/t.bZ : Lcom/tencent/wxop/stat/b/b;
    //   422: aload_1
    //   423: invokevirtual b : (Ljava/lang/Throwable;)V
    //   426: aload #7
    //   428: ifnull -> 21
    //   431: aload #7
    //   433: invokevirtual endTransaction : ()V
    //   436: goto -> 21
    //   439: astore_1
    //   440: getstatic com/tencent/wxop/stat/t.bZ : Lcom/tencent/wxop/stat/b/b;
    //   443: aload_1
    //   444: invokevirtual b : (Ljava/lang/Throwable;)V
    //   447: goto -> 21
    //   450: astore_1
    //   451: aconst_null
    //   452: astore #8
    //   454: aload #8
    //   456: ifnull -> 464
    //   459: aload #8
    //   461: invokevirtual endTransaction : ()V
    //   464: aload_1
    //   465: athrow
    //   466: astore #8
    //   468: getstatic com/tencent/wxop/stat/t.bZ : Lcom/tencent/wxop/stat/b/b;
    //   471: aload #8
    //   473: invokevirtual b : (Ljava/lang/Throwable;)V
    //   476: goto -> 464
    //   479: astore_1
    //   480: goto -> 454
    //   483: astore_1
    //   484: goto -> 415
    // Exception table:
    //   from	to	target	type
    //   8	16	283	finally
    //   28	33	283	finally
    //   33	40	411	java/lang/Throwable
    //   33	40	450	finally
    //   49	54	483	java/lang/Throwable
    //   49	54	479	finally
    //   58	66	483	java/lang/Throwable
    //   58	66	479	finally
    //   70	94	483	java/lang/Throwable
    //   70	94	479	finally
    //   105	111	483	java/lang/Throwable
    //   105	111	479	finally
    //   115	120	483	java/lang/Throwable
    //   115	120	479	finally
    //   124	129	483	java/lang/Throwable
    //   124	129	479	finally
    //   133	141	483	java/lang/Throwable
    //   133	141	479	finally
    //   145	160	483	java/lang/Throwable
    //   145	160	479	finally
    //   164	169	483	java/lang/Throwable
    //   164	169	479	finally
    //   173	180	483	java/lang/Throwable
    //   173	180	479	finally
    //   188	193	483	java/lang/Throwable
    //   188	193	479	finally
    //   197	202	483	java/lang/Throwable
    //   197	202	479	finally
    //   206	214	483	java/lang/Throwable
    //   206	214	479	finally
    //   218	232	483	java/lang/Throwable
    //   218	232	479	finally
    //   236	242	483	java/lang/Throwable
    //   236	242	479	finally
    //   246	250	483	java/lang/Throwable
    //   246	250	479	finally
    //   254	259	483	java/lang/Throwable
    //   254	259	479	finally
    //   264	269	272	java/lang/Throwable
    //   264	269	283	finally
    //   273	280	283	finally
    //   288	293	283	finally
    //   300	305	483	java/lang/Throwable
    //   300	305	479	finally
    //   309	317	483	java/lang/Throwable
    //   309	317	479	finally
    //   321	345	483	java/lang/Throwable
    //   321	345	479	finally
    //   352	361	483	java/lang/Throwable
    //   352	361	479	finally
    //   365	369	483	java/lang/Throwable
    //   365	369	479	finally
    //   373	380	483	java/lang/Throwable
    //   373	380	479	finally
    //   384	394	483	java/lang/Throwable
    //   384	394	479	finally
    //   398	408	483	java/lang/Throwable
    //   398	408	479	finally
    //   419	426	479	finally
    //   431	436	439	java/lang/Throwable
    //   431	436	283	finally
    //   440	447	283	finally
    //   459	464	466	java/lang/Throwable
    //   459	464	283	finally
    //   464	466	283	finally
    //   468	476	283	finally
  }
  
  private void a(List<ad> paramList, boolean paramBoolean) {
    // Byte code:
    //   0: aconst_null
    //   1: astore_3
    //   2: aconst_null
    //   3: astore #4
    //   5: aload_0
    //   6: monitorenter
    //   7: aload_1
    //   8: invokeinterface size : ()I
    //   13: istore #5
    //   15: iload #5
    //   17: ifne -> 23
    //   20: aload_0
    //   21: monitorexit
    //   22: return
    //   23: invokestatic k : ()Z
    //   26: ifeq -> 76
    //   29: getstatic com/tencent/wxop/stat/t.bZ : Lcom/tencent/wxop/stat/b/b;
    //   32: astore #6
    //   34: new java/lang/StringBuilder
    //   37: astore #7
    //   39: aload #7
    //   41: ldc_w 'Delete '
    //   44: invokespecial <init> : (Ljava/lang/String;)V
    //   47: aload #6
    //   49: aload #7
    //   51: aload_1
    //   52: invokeinterface size : ()I
    //   57: invokevirtual append : (I)Ljava/lang/StringBuilder;
    //   60: ldc_w ' events, important:'
    //   63: invokevirtual append : (Ljava/lang/String;)Ljava/lang/StringBuilder;
    //   66: iload_2
    //   67: invokevirtual append : (Z)Ljava/lang/StringBuilder;
    //   70: invokevirtual toString : ()Ljava/lang/String;
    //   73: invokevirtual b : (Ljava/lang/Object;)V
    //   76: new java/lang/StringBuilder
    //   79: astore #6
    //   81: aload #6
    //   83: aload_1
    //   84: invokeinterface size : ()I
    //   89: iconst_3
    //   90: imul
    //   91: invokespecial <init> : (I)V
    //   94: aload #6
    //   96: ldc_w 'event_id in ('
    //   99: invokevirtual append : (Ljava/lang/String;)Ljava/lang/StringBuilder;
    //   102: pop
    //   103: aload_1
    //   104: invokeinterface size : ()I
    //   109: istore #8
    //   111: aload_1
    //   112: invokeinterface iterator : ()Ljava/util/Iterator;
    //   117: astore_1
    //   118: iconst_0
    //   119: istore #5
    //   121: aload_1
    //   122: invokeinterface hasNext : ()Z
    //   127: ifeq -> 172
    //   130: aload #6
    //   132: aload_1
    //   133: invokeinterface next : ()Ljava/lang/Object;
    //   138: checkcast com/tencent/wxop/stat/ad
    //   141: getfield K : J
    //   144: invokevirtual append : (J)Ljava/lang/StringBuilder;
    //   147: pop
    //   148: iload #5
    //   150: iload #8
    //   152: iconst_1
    //   153: isub
    //   154: if_icmpeq -> 166
    //   157: aload #6
    //   159: ldc_w ','
    //   162: invokevirtual append : (Ljava/lang/String;)Ljava/lang/StringBuilder;
    //   165: pop
    //   166: iinc #5, 1
    //   169: goto -> 121
    //   172: aload #6
    //   174: ldc_w ')'
    //   177: invokevirtual append : (Ljava/lang/String;)Ljava/lang/StringBuilder;
    //   180: pop
    //   181: aload_3
    //   182: astore_1
    //   183: aload_0
    //   184: iload_2
    //   185: invokespecial c : (Z)Landroid/database/sqlite/SQLiteDatabase;
    //   188: astore_3
    //   189: aload_3
    //   190: astore #4
    //   192: aload_3
    //   193: astore_1
    //   194: aload_3
    //   195: invokevirtual beginTransaction : ()V
    //   198: aload_3
    //   199: astore #4
    //   201: aload_3
    //   202: astore_1
    //   203: aload_3
    //   204: ldc_w 'events'
    //   207: aload #6
    //   209: invokevirtual toString : ()Ljava/lang/String;
    //   212: aconst_null
    //   213: invokevirtual delete : (Ljava/lang/String;Ljava/lang/String;[Ljava/lang/String;)I
    //   216: istore #5
    //   218: aload_3
    //   219: astore #4
    //   221: aload_3
    //   222: astore_1
    //   223: invokestatic k : ()Z
    //   226: ifeq -> 307
    //   229: aload_3
    //   230: astore #4
    //   232: aload_3
    //   233: astore_1
    //   234: getstatic com/tencent/wxop/stat/t.bZ : Lcom/tencent/wxop/stat/b/b;
    //   237: astore #7
    //   239: aload_3
    //   240: astore #4
    //   242: aload_3
    //   243: astore_1
    //   244: new java/lang/StringBuilder
    //   247: astore #9
    //   249: aload_3
    //   250: astore #4
    //   252: aload_3
    //   253: astore_1
    //   254: aload #9
    //   256: ldc_w 'delete '
    //   259: invokespecial <init> : (Ljava/lang/String;)V
    //   262: aload_3
    //   263: astore #4
    //   265: aload_3
    //   266: astore_1
    //   267: aload #7
    //   269: aload #9
    //   271: iload #8
    //   273: invokevirtual append : (I)Ljava/lang/StringBuilder;
    //   276: ldc_w ' event '
    //   279: invokevirtual append : (Ljava/lang/String;)Ljava/lang/StringBuilder;
    //   282: aload #6
    //   284: invokevirtual toString : ()Ljava/lang/String;
    //   287: invokevirtual append : (Ljava/lang/String;)Ljava/lang/StringBuilder;
    //   290: ldc_w ', success delete:'
    //   293: invokevirtual append : (Ljava/lang/String;)Ljava/lang/StringBuilder;
    //   296: iload #5
    //   298: invokevirtual append : (I)Ljava/lang/StringBuilder;
    //   301: invokevirtual toString : ()Ljava/lang/String;
    //   304: invokevirtual b : (Ljava/lang/Object;)V
    //   307: aload_3
    //   308: astore #4
    //   310: aload_3
    //   311: astore_1
    //   312: aload_0
    //   313: aload_0
    //   314: getfield aI : I
    //   317: iload #5
    //   319: isub
    //   320: putfield aI : I
    //   323: aload_3
    //   324: astore #4
    //   326: aload_3
    //   327: astore_1
    //   328: aload_3
    //   329: invokevirtual setTransactionSuccessful : ()V
    //   332: aload_3
    //   333: astore #4
    //   335: aload_3
    //   336: astore_1
    //   337: aload_0
    //   338: invokespecial aj : ()V
    //   341: aload_3
    //   342: ifnull -> 20
    //   345: aload_3
    //   346: invokevirtual endTransaction : ()V
    //   349: goto -> 20
    //   352: astore_1
    //   353: getstatic com/tencent/wxop/stat/t.bZ : Lcom/tencent/wxop/stat/b/b;
    //   356: aload_1
    //   357: invokevirtual b : (Ljava/lang/Throwable;)V
    //   360: goto -> 20
    //   363: astore_1
    //   364: aload_0
    //   365: monitorexit
    //   366: aload_1
    //   367: athrow
    //   368: astore_3
    //   369: aload #4
    //   371: astore_1
    //   372: getstatic com/tencent/wxop/stat/t.bZ : Lcom/tencent/wxop/stat/b/b;
    //   375: aload_3
    //   376: invokevirtual b : (Ljava/lang/Throwable;)V
    //   379: aload #4
    //   381: ifnull -> 20
    //   384: aload #4
    //   386: invokevirtual endTransaction : ()V
    //   389: goto -> 20
    //   392: astore_1
    //   393: getstatic com/tencent/wxop/stat/t.bZ : Lcom/tencent/wxop/stat/b/b;
    //   396: aload_1
    //   397: invokevirtual b : (Ljava/lang/Throwable;)V
    //   400: goto -> 20
    //   403: astore #4
    //   405: aload_1
    //   406: ifnull -> 413
    //   409: aload_1
    //   410: invokevirtual endTransaction : ()V
    //   413: aload #4
    //   415: athrow
    //   416: astore_1
    //   417: getstatic com/tencent/wxop/stat/t.bZ : Lcom/tencent/wxop/stat/b/b;
    //   420: aload_1
    //   421: invokevirtual b : (Ljava/lang/Throwable;)V
    //   424: goto -> 413
    // Exception table:
    //   from	to	target	type
    //   7	15	363	finally
    //   23	76	363	finally
    //   76	118	363	finally
    //   121	148	363	finally
    //   157	166	363	finally
    //   172	181	363	finally
    //   183	189	368	java/lang/Throwable
    //   183	189	403	finally
    //   194	198	368	java/lang/Throwable
    //   194	198	403	finally
    //   203	218	368	java/lang/Throwable
    //   203	218	403	finally
    //   223	229	368	java/lang/Throwable
    //   223	229	403	finally
    //   234	239	368	java/lang/Throwable
    //   234	239	403	finally
    //   244	249	368	java/lang/Throwable
    //   244	249	403	finally
    //   254	262	368	java/lang/Throwable
    //   254	262	403	finally
    //   267	307	368	java/lang/Throwable
    //   267	307	403	finally
    //   312	323	368	java/lang/Throwable
    //   312	323	403	finally
    //   328	332	368	java/lang/Throwable
    //   328	332	403	finally
    //   337	341	368	java/lang/Throwable
    //   337	341	403	finally
    //   345	349	352	java/lang/Throwable
    //   345	349	363	finally
    //   353	360	363	finally
    //   372	379	403	finally
    //   384	389	392	java/lang/Throwable
    //   384	389	363	finally
    //   393	400	363	finally
    //   409	413	416	java/lang/Throwable
    //   409	413	363	finally
    //   413	416	363	finally
    //   417	424	363	finally
  }
  
  public static t ai() {
    return cb;
  }
  
  private void aj() {
    this.aI = ak() + al();
  }
  
  private int ak() {
    return (int)DatabaseUtils.queryNumEntries(this.bW.getReadableDatabase(), "events");
  }
  
  private int al() {
    return (int)DatabaseUtils.queryNumEntries(this.bX.getReadableDatabase(), "events");
  }
  
  private void am() {
    // Byte code:
    //   0: aconst_null
    //   1: astore_1
    //   2: aconst_null
    //   3: astore_2
    //   4: aload_0
    //   5: getfield ce : Z
    //   8: ifeq -> 12
    //   11: return
    //   12: aload_0
    //   13: getfield cd : Ljava/util/concurrent/ConcurrentHashMap;
    //   16: astore_3
    //   17: aload_3
    //   18: monitorenter
    //   19: aload_0
    //   20: getfield cd : Ljava/util/concurrent/ConcurrentHashMap;
    //   23: invokevirtual size : ()I
    //   26: ifne -> 39
    //   29: aload_3
    //   30: monitorexit
    //   31: goto -> 11
    //   34: astore_2
    //   35: aload_3
    //   36: monitorexit
    //   37: aload_2
    //   38: athrow
    //   39: aload_0
    //   40: iconst_1
    //   41: putfield ce : Z
    //   44: invokestatic k : ()Z
    //   47: ifeq -> 113
    //   50: getstatic com/tencent/wxop/stat/t.bZ : Lcom/tencent/wxop/stat/b/b;
    //   53: astore #4
    //   55: new java/lang/StringBuilder
    //   58: astore #5
    //   60: aload #5
    //   62: ldc_w 'insert '
    //   65: invokespecial <init> : (Ljava/lang/String;)V
    //   68: aload #4
    //   70: aload #5
    //   72: aload_0
    //   73: getfield cd : Ljava/util/concurrent/ConcurrentHashMap;
    //   76: invokevirtual size : ()I
    //   79: invokevirtual append : (I)Ljava/lang/StringBuilder;
    //   82: ldc_w ' events ,numEventsCachedInMemory:'
    //   85: invokevirtual append : (Ljava/lang/String;)Ljava/lang/StringBuilder;
    //   88: getstatic com/tencent/wxop/stat/c.ay : I
    //   91: invokevirtual append : (I)Ljava/lang/StringBuilder;
    //   94: ldc_w ',numStoredEvents:'
    //   97: invokevirtual append : (Ljava/lang/String;)Ljava/lang/StringBuilder;
    //   100: aload_0
    //   101: getfield aI : I
    //   104: invokevirtual append : (I)Ljava/lang/StringBuilder;
    //   107: invokevirtual toString : ()Ljava/lang/String;
    //   110: invokevirtual b : (Ljava/lang/Object;)V
    //   113: aload_0
    //   114: getfield bW : Lcom/tencent/wxop/stat/ac;
    //   117: invokevirtual getWritableDatabase : ()Landroid/database/sqlite/SQLiteDatabase;
    //   120: astore #4
    //   122: aload #4
    //   124: astore_2
    //   125: aload #4
    //   127: astore_1
    //   128: aload #4
    //   130: invokevirtual beginTransaction : ()V
    //   133: aload #4
    //   135: astore_2
    //   136: aload #4
    //   138: astore_1
    //   139: aload_0
    //   140: getfield cd : Ljava/util/concurrent/ConcurrentHashMap;
    //   143: invokevirtual entrySet : ()Ljava/util/Set;
    //   146: invokeinterface iterator : ()Ljava/util/Iterator;
    //   151: astore #5
    //   153: aload #4
    //   155: astore_2
    //   156: aload #4
    //   158: astore_1
    //   159: aload #5
    //   161: invokeinterface hasNext : ()Z
    //   166: ifeq -> 507
    //   169: aload #4
    //   171: astore_2
    //   172: aload #4
    //   174: astore_1
    //   175: aload #5
    //   177: invokeinterface next : ()Ljava/lang/Object;
    //   182: checkcast java/util/Map$Entry
    //   185: invokeinterface getKey : ()Ljava/lang/Object;
    //   190: checkcast com/tencent/wxop/stat/a/d
    //   193: astore #6
    //   195: aload #4
    //   197: astore_2
    //   198: aload #4
    //   200: astore_1
    //   201: new android/content/ContentValues
    //   204: astore #7
    //   206: aload #4
    //   208: astore_2
    //   209: aload #4
    //   211: astore_1
    //   212: aload #7
    //   214: invokespecial <init> : ()V
    //   217: aload #4
    //   219: astore_2
    //   220: aload #4
    //   222: astore_1
    //   223: aload #6
    //   225: invokevirtual af : ()Ljava/lang/String;
    //   228: astore #8
    //   230: aload #4
    //   232: astore_2
    //   233: aload #4
    //   235: astore_1
    //   236: invokestatic k : ()Z
    //   239: ifeq -> 299
    //   242: aload #4
    //   244: astore_2
    //   245: aload #4
    //   247: astore_1
    //   248: getstatic com/tencent/wxop/stat/t.bZ : Lcom/tencent/wxop/stat/b/b;
    //   251: astore #9
    //   253: aload #4
    //   255: astore_2
    //   256: aload #4
    //   258: astore_1
    //   259: new java/lang/StringBuilder
    //   262: astore #10
    //   264: aload #4
    //   266: astore_2
    //   267: aload #4
    //   269: astore_1
    //   270: aload #10
    //   272: ldc_w 'insert content:'
    //   275: invokespecial <init> : (Ljava/lang/String;)V
    //   278: aload #4
    //   280: astore_2
    //   281: aload #4
    //   283: astore_1
    //   284: aload #9
    //   286: aload #10
    //   288: aload #8
    //   290: invokevirtual append : (Ljava/lang/String;)Ljava/lang/StringBuilder;
    //   293: invokevirtual toString : ()Ljava/lang/String;
    //   296: invokevirtual b : (Ljava/lang/Object;)V
    //   299: aload #4
    //   301: astore_2
    //   302: aload #4
    //   304: astore_1
    //   305: aload #7
    //   307: ldc_w 'content'
    //   310: aload #8
    //   312: invokestatic q : (Ljava/lang/String;)Ljava/lang/String;
    //   315: invokevirtual put : (Ljava/lang/String;Ljava/lang/String;)V
    //   318: aload #4
    //   320: astore_2
    //   321: aload #4
    //   323: astore_1
    //   324: aload #7
    //   326: ldc_w 'send_count'
    //   329: ldc_w '0'
    //   332: invokevirtual put : (Ljava/lang/String;Ljava/lang/String;)V
    //   335: aload #4
    //   337: astore_2
    //   338: aload #4
    //   340: astore_1
    //   341: aload #7
    //   343: ldc_w 'status'
    //   346: iconst_1
    //   347: invokestatic toString : (I)Ljava/lang/String;
    //   350: invokevirtual put : (Ljava/lang/String;Ljava/lang/String;)V
    //   353: aload #4
    //   355: astore_2
    //   356: aload #4
    //   358: astore_1
    //   359: aload #7
    //   361: ldc_w 'timestamp'
    //   364: aload #6
    //   366: invokevirtual ad : ()J
    //   369: invokestatic valueOf : (J)Ljava/lang/Long;
    //   372: invokevirtual put : (Ljava/lang/String;Ljava/lang/Long;)V
    //   375: aload #4
    //   377: astore_2
    //   378: aload #4
    //   380: astore_1
    //   381: aload #4
    //   383: ldc_w 'events'
    //   386: aconst_null
    //   387: aload #7
    //   389: invokevirtual insert : (Ljava/lang/String;Ljava/lang/String;Landroid/content/ContentValues;)J
    //   392: pop2
    //   393: aload #4
    //   395: astore_2
    //   396: aload #4
    //   398: astore_1
    //   399: aload #5
    //   401: invokeinterface remove : ()V
    //   406: goto -> 153
    //   409: astore #4
    //   411: aload_2
    //   412: astore_1
    //   413: getstatic com/tencent/wxop/stat/t.bZ : Lcom/tencent/wxop/stat/b/b;
    //   416: aload #4
    //   418: invokevirtual b : (Ljava/lang/Throwable;)V
    //   421: aload_2
    //   422: ifnull -> 433
    //   425: aload_2
    //   426: invokevirtual endTransaction : ()V
    //   429: aload_0
    //   430: invokespecial aj : ()V
    //   433: aload_0
    //   434: iconst_0
    //   435: putfield ce : Z
    //   438: invokestatic k : ()Z
    //   441: ifeq -> 502
    //   444: getstatic com/tencent/wxop/stat/t.bZ : Lcom/tencent/wxop/stat/b/b;
    //   447: astore_2
    //   448: new java/lang/StringBuilder
    //   451: astore_1
    //   452: aload_1
    //   453: ldc_w 'after insert, cacheEventsInMemory.size():'
    //   456: invokespecial <init> : (Ljava/lang/String;)V
    //   459: aload_2
    //   460: aload_1
    //   461: aload_0
    //   462: getfield cd : Ljava/util/concurrent/ConcurrentHashMap;
    //   465: invokevirtual size : ()I
    //   468: invokevirtual append : (I)Ljava/lang/StringBuilder;
    //   471: ldc_w ',numEventsCachedInMemory:'
    //   474: invokevirtual append : (Ljava/lang/String;)Ljava/lang/StringBuilder;
    //   477: getstatic com/tencent/wxop/stat/c.ay : I
    //   480: invokevirtual append : (I)Ljava/lang/StringBuilder;
    //   483: ldc_w ',numStoredEvents:'
    //   486: invokevirtual append : (Ljava/lang/String;)Ljava/lang/StringBuilder;
    //   489: aload_0
    //   490: getfield aI : I
    //   493: invokevirtual append : (I)Ljava/lang/StringBuilder;
    //   496: invokevirtual toString : ()Ljava/lang/String;
    //   499: invokevirtual b : (Ljava/lang/Object;)V
    //   502: aload_3
    //   503: monitorexit
    //   504: goto -> 11
    //   507: aload #4
    //   509: astore_2
    //   510: aload #4
    //   512: astore_1
    //   513: aload #4
    //   515: invokevirtual setTransactionSuccessful : ()V
    //   518: aload #4
    //   520: ifnull -> 433
    //   523: aload #4
    //   525: invokevirtual endTransaction : ()V
    //   528: aload_0
    //   529: invokespecial aj : ()V
    //   532: goto -> 433
    //   535: astore_2
    //   536: getstatic com/tencent/wxop/stat/t.bZ : Lcom/tencent/wxop/stat/b/b;
    //   539: aload_2
    //   540: invokevirtual b : (Ljava/lang/Throwable;)V
    //   543: goto -> 433
    //   546: astore_2
    //   547: getstatic com/tencent/wxop/stat/t.bZ : Lcom/tencent/wxop/stat/b/b;
    //   550: aload_2
    //   551: invokevirtual b : (Ljava/lang/Throwable;)V
    //   554: goto -> 433
    //   557: astore_2
    //   558: aload_1
    //   559: ifnull -> 570
    //   562: aload_1
    //   563: invokevirtual endTransaction : ()V
    //   566: aload_0
    //   567: invokespecial aj : ()V
    //   570: aload_2
    //   571: athrow
    //   572: astore_1
    //   573: getstatic com/tencent/wxop/stat/t.bZ : Lcom/tencent/wxop/stat/b/b;
    //   576: aload_1
    //   577: invokevirtual b : (Ljava/lang/Throwable;)V
    //   580: goto -> 570
    // Exception table:
    //   from	to	target	type
    //   19	31	34	finally
    //   39	113	34	finally
    //   113	122	409	java/lang/Throwable
    //   113	122	557	finally
    //   128	133	409	java/lang/Throwable
    //   128	133	557	finally
    //   139	153	409	java/lang/Throwable
    //   139	153	557	finally
    //   159	169	409	java/lang/Throwable
    //   159	169	557	finally
    //   175	195	409	java/lang/Throwable
    //   175	195	557	finally
    //   201	206	409	java/lang/Throwable
    //   201	206	557	finally
    //   212	217	409	java/lang/Throwable
    //   212	217	557	finally
    //   223	230	409	java/lang/Throwable
    //   223	230	557	finally
    //   236	242	409	java/lang/Throwable
    //   236	242	557	finally
    //   248	253	409	java/lang/Throwable
    //   248	253	557	finally
    //   259	264	409	java/lang/Throwable
    //   259	264	557	finally
    //   270	278	409	java/lang/Throwable
    //   270	278	557	finally
    //   284	299	409	java/lang/Throwable
    //   284	299	557	finally
    //   305	318	409	java/lang/Throwable
    //   305	318	557	finally
    //   324	335	409	java/lang/Throwable
    //   324	335	557	finally
    //   341	353	409	java/lang/Throwable
    //   341	353	557	finally
    //   359	375	409	java/lang/Throwable
    //   359	375	557	finally
    //   381	393	409	java/lang/Throwable
    //   381	393	557	finally
    //   399	406	409	java/lang/Throwable
    //   399	406	557	finally
    //   413	421	557	finally
    //   425	433	546	java/lang/Throwable
    //   425	433	34	finally
    //   433	502	34	finally
    //   502	504	34	finally
    //   513	518	409	java/lang/Throwable
    //   513	518	557	finally
    //   523	532	535	java/lang/Throwable
    //   523	532	34	finally
    //   536	543	34	finally
    //   547	554	34	finally
    //   562	570	572	java/lang/Throwable
    //   562	570	34	finally
    //   570	572	34	finally
    //   573	580	34	finally
  }
  
  private void an() {
    // Byte code:
    //   0: aload_0
    //   1: getfield bW : Lcom/tencent/wxop/stat/ac;
    //   4: invokevirtual getReadableDatabase : ()Landroid/database/sqlite/SQLiteDatabase;
    //   7: ldc_w 'keyvalues'
    //   10: aconst_null
    //   11: aconst_null
    //   12: aconst_null
    //   13: aconst_null
    //   14: aconst_null
    //   15: aconst_null
    //   16: invokevirtual query : (Ljava/lang/String;[Ljava/lang/String;Ljava/lang/String;[Ljava/lang/String;Ljava/lang/String;Ljava/lang/String;Ljava/lang/String;)Landroid/database/Cursor;
    //   19: astore_1
    //   20: aload_1
    //   21: astore_2
    //   22: aload_1
    //   23: invokeinterface moveToNext : ()Z
    //   28: ifeq -> 79
    //   31: aload_1
    //   32: astore_2
    //   33: aload_0
    //   34: getfield cf : Ljava/util/HashMap;
    //   37: aload_1
    //   38: iconst_0
    //   39: invokeinterface getString : (I)Ljava/lang/String;
    //   44: aload_1
    //   45: iconst_1
    //   46: invokeinterface getString : (I)Ljava/lang/String;
    //   51: invokevirtual put : (Ljava/lang/Object;Ljava/lang/Object;)Ljava/lang/Object;
    //   54: pop
    //   55: goto -> 20
    //   58: astore_3
    //   59: aload_1
    //   60: astore_2
    //   61: getstatic com/tencent/wxop/stat/t.bZ : Lcom/tencent/wxop/stat/b/b;
    //   64: aload_3
    //   65: invokevirtual b : (Ljava/lang/Throwable;)V
    //   68: aload_1
    //   69: ifnull -> 78
    //   72: aload_1
    //   73: invokeinterface close : ()V
    //   78: return
    //   79: aload_1
    //   80: ifnull -> 78
    //   83: aload_1
    //   84: invokeinterface close : ()V
    //   89: goto -> 78
    //   92: astore_1
    //   93: aconst_null
    //   94: astore_2
    //   95: aload_2
    //   96: ifnull -> 105
    //   99: aload_2
    //   100: invokeinterface close : ()V
    //   105: aload_1
    //   106: athrow
    //   107: astore_1
    //   108: goto -> 95
    //   111: astore_3
    //   112: aconst_null
    //   113: astore_1
    //   114: goto -> 59
    // Exception table:
    //   from	to	target	type
    //   0	20	111	java/lang/Throwable
    //   0	20	92	finally
    //   22	31	58	java/lang/Throwable
    //   22	31	107	finally
    //   33	55	58	java/lang/Throwable
    //   33	55	107	finally
    //   61	68	107	finally
  }
  
  private static String b(List<ad> paramList) {
    StringBuilder stringBuilder = new StringBuilder(paramList.size() * 3);
    stringBuilder.append("event_id in (");
    int i = paramList.size();
    Iterator<ad> iterator = paramList.iterator();
    for (byte b1 = 0; iterator.hasNext(); b1++) {
      stringBuilder.append(((ad)iterator.next()).K);
      if (b1 != i - 1)
        stringBuilder.append(","); 
    } 
    stringBuilder.append(")");
    return stringBuilder.toString();
  }
  
  private void b(List<ad> paramList, int paramInt, boolean paramBoolean) {
    String str;
    if (!paramBoolean) {
      try {
        SQLiteDatabase sQLiteDatabase = this.bW.getReadableDatabase();
        String str1 = Integer.toString(1);
      } catch (Throwable throwable) {
      
      } finally {
        Cursor cursor = null;
        if (cursor != null)
          cursor.close(); 
      } 
    } else {
      SQLiteDatabase sQLiteDatabase = this.bX.getReadableDatabase();
      String str1 = Integer.toString(1);
      str = Integer.toString(paramInt);
      Cursor cursor = sQLiteDatabase.query("events", null, "status=?", new String[] { str1 }, null, null, null, str);
    } 
    try {
      return;
    } finally {
      String str1;
      str = null;
      List<ad> list = paramList;
    } 
  }
  
  private void b(boolean paramBoolean) {
    Throwable throwable;
    SQLiteDatabase sQLiteDatabase1 = null;
    SQLiteDatabase sQLiteDatabase2 = null;
    try {
      SQLiteDatabase sQLiteDatabase = c(paramBoolean);
      sQLiteDatabase2 = sQLiteDatabase;
      sQLiteDatabase1 = sQLiteDatabase;
      sQLiteDatabase.beginTransaction();
      sQLiteDatabase2 = sQLiteDatabase;
      sQLiteDatabase1 = sQLiteDatabase;
      ContentValues contentValues = new ContentValues();
      sQLiteDatabase2 = sQLiteDatabase;
      sQLiteDatabase1 = sQLiteDatabase;
      this();
      sQLiteDatabase2 = sQLiteDatabase;
      sQLiteDatabase1 = sQLiteDatabase;
      contentValues.put("status", Integer.valueOf(1));
      sQLiteDatabase2 = sQLiteDatabase;
      sQLiteDatabase1 = sQLiteDatabase;
      int i = sQLiteDatabase.update("events", contentValues, "status=?", new String[] { Long.toString(2L) });
      sQLiteDatabase2 = sQLiteDatabase;
      sQLiteDatabase1 = sQLiteDatabase;
      if (c.k()) {
        sQLiteDatabase2 = sQLiteDatabase;
        sQLiteDatabase1 = sQLiteDatabase;
        b b1 = bZ;
        sQLiteDatabase2 = sQLiteDatabase;
        sQLiteDatabase1 = sQLiteDatabase;
        StringBuilder stringBuilder = new StringBuilder();
        sQLiteDatabase2 = sQLiteDatabase;
        sQLiteDatabase1 = sQLiteDatabase;
        this("update ");
        sQLiteDatabase2 = sQLiteDatabase;
        sQLiteDatabase1 = sQLiteDatabase;
        b1.b(stringBuilder.append(i).append(" unsent events.").toString());
      } 
      sQLiteDatabase2 = sQLiteDatabase;
      sQLiteDatabase1 = sQLiteDatabase;
      sQLiteDatabase.setTransactionSuccessful();
      return;
    } catch (Throwable throwable1) {
      throwable = null;
      bZ.b(throwable1);
      return;
    } finally {
      if (throwable != null)
        try {
          throwable.endTransaction();
        } catch (Throwable throwable1) {
          bZ.b(throwable1);
        }  
    } 
  }
  
  private SQLiteDatabase c(boolean paramBoolean) {
    return !paramBoolean ? this.bW.getWritableDatabase() : this.bX.getWritableDatabase();
  }
  
  public static t s(Context paramContext) {
    // Byte code:
    //   0: getstatic com/tencent/wxop/stat/t.cb : Lcom/tencent/wxop/stat/t;
    //   3: ifnonnull -> 31
    //   6: ldc com/tencent/wxop/stat/t
    //   8: monitorenter
    //   9: getstatic com/tencent/wxop/stat/t.cb : Lcom/tencent/wxop/stat/t;
    //   12: ifnonnull -> 28
    //   15: new com/tencent/wxop/stat/t
    //   18: astore_1
    //   19: aload_1
    //   20: aload_0
    //   21: invokespecial <init> : (Landroid/content/Context;)V
    //   24: aload_1
    //   25: putstatic com/tencent/wxop/stat/t.cb : Lcom/tencent/wxop/stat/t;
    //   28: ldc com/tencent/wxop/stat/t
    //   30: monitorexit
    //   31: getstatic com/tencent/wxop/stat/t.cb : Lcom/tencent/wxop/stat/t;
    //   34: areturn
    //   35: astore_0
    //   36: ldc com/tencent/wxop/stat/t
    //   38: monitorexit
    //   39: aload_0
    //   40: athrow
    // Exception table:
    //   from	to	target	type
    //   9	28	35	finally
    //   28	31	35	finally
  }
  
  final void H() {
    if (c.l())
      try {
        f f1 = this.be;
        w w = new w();
        this(this);
        f1.a(w);
      } catch (Throwable throwable) {
        bZ.b(throwable);
      }  
  }
  
  final void b(int paramInt) {
    this.be.a(new ab(this, paramInt));
  }
  
  final void b(d paramd, aj paramaj, boolean paramBoolean1, boolean paramBoolean2) {
    if (this.be != null)
      this.be.a(new x(this, paramd, paramaj, paramBoolean1, paramBoolean2)); 
  }
  
  final void b(ah paramah) {
    if (paramah != null)
      this.be.a(new y(this, paramah)); 
  }
  
  final void b(List<ad> paramList, boolean paramBoolean) {
    if (this.be != null)
      this.be.a(new u(this, paramList, paramBoolean)); 
  }
  
  final void c(List<ad> paramList, boolean paramBoolean) {
    if (this.be != null)
      this.be.a(new v(this, paramList, paramBoolean)); 
  }
  
  public final int r() {
    return this.aI;
  }
  
  public final c t(Context paramContext) {
    // Byte code:
    //   0: aload_0
    //   1: monitorenter
    //   2: aload_0
    //   3: getfield bY : Lcom/tencent/wxop/stat/b/c;
    //   6: ifnull -> 18
    //   9: aload_0
    //   10: getfield bY : Lcom/tencent/wxop/stat/b/c;
    //   13: astore_1
    //   14: aload_0
    //   15: monitorexit
    //   16: aload_1
    //   17: areturn
    //   18: aload_0
    //   19: getfield bW : Lcom/tencent/wxop/stat/ac;
    //   22: invokevirtual getWritableDatabase : ()Landroid/database/sqlite/SQLiteDatabase;
    //   25: invokevirtual beginTransaction : ()V
    //   28: invokestatic k : ()Z
    //   31: ifeq -> 43
    //   34: getstatic com/tencent/wxop/stat/t.bZ : Lcom/tencent/wxop/stat/b/b;
    //   37: ldc_w 'try to load user info from db.'
    //   40: invokevirtual b : (Ljava/lang/Object;)V
    //   43: aload_0
    //   44: getfield bW : Lcom/tencent/wxop/stat/ac;
    //   47: invokevirtual getReadableDatabase : ()Landroid/database/sqlite/SQLiteDatabase;
    //   50: ldc_w 'user'
    //   53: aconst_null
    //   54: aconst_null
    //   55: aconst_null
    //   56: aconst_null
    //   57: aconst_null
    //   58: aconst_null
    //   59: aconst_null
    //   60: invokevirtual query : (Ljava/lang/String;[Ljava/lang/String;Ljava/lang/String;[Ljava/lang/String;Ljava/lang/String;Ljava/lang/String;Ljava/lang/String;Ljava/lang/String;)Landroid/database/Cursor;
    //   63: astore_2
    //   64: iconst_0
    //   65: istore_3
    //   66: aload_2
    //   67: invokeinterface moveToNext : ()Z
    //   72: ifeq -> 458
    //   75: aload_2
    //   76: iconst_0
    //   77: invokeinterface getString : (I)Ljava/lang/String;
    //   82: astore #4
    //   84: aload #4
    //   86: invokestatic t : (Ljava/lang/String;)Ljava/lang/String;
    //   89: astore #5
    //   91: aload_2
    //   92: iconst_1
    //   93: invokeinterface getInt : (I)I
    //   98: istore #6
    //   100: aload_2
    //   101: iconst_2
    //   102: invokeinterface getString : (I)Ljava/lang/String;
    //   107: astore #7
    //   109: aload_2
    //   110: iconst_3
    //   111: invokeinterface getLong : (I)J
    //   116: lstore #8
    //   118: invokestatic currentTimeMillis : ()J
    //   121: ldc2_w 1000
    //   124: ldiv
    //   125: lstore #10
    //   127: iload #6
    //   129: iconst_1
    //   130: if_icmpeq -> 918
    //   133: lload #8
    //   135: ldc2_w 1000
    //   138: lmul
    //   139: invokestatic d : (J)Ljava/lang/String;
    //   142: ldc2_w 1000
    //   145: lload #10
    //   147: lmul
    //   148: invokestatic d : (J)Ljava/lang/String;
    //   151: invokevirtual equals : (Ljava/lang/Object;)Z
    //   154: ifne -> 918
    //   157: iconst_1
    //   158: istore_3
    //   159: aload #7
    //   161: aload_1
    //   162: invokestatic G : (Landroid/content/Context;)Ljava/lang/String;
    //   165: invokevirtual equals : (Ljava/lang/Object;)Z
    //   168: ifne -> 912
    //   171: iload_3
    //   172: iconst_2
    //   173: ior
    //   174: istore #12
    //   176: aload #5
    //   178: ldc_w ','
    //   181: invokevirtual split : (Ljava/lang/String;)[Ljava/lang/String;
    //   184: astore #13
    //   186: iconst_0
    //   187: istore #14
    //   189: iconst_0
    //   190: istore_3
    //   191: aload #13
    //   193: ifnull -> 664
    //   196: aload #13
    //   198: arraylength
    //   199: ifle -> 664
    //   202: aload #13
    //   204: iconst_0
    //   205: aaload
    //   206: astore #7
    //   208: aload #7
    //   210: ifnull -> 223
    //   213: aload #7
    //   215: invokevirtual length : ()I
    //   218: bipush #11
    //   220: if_icmpge -> 894
    //   223: aload_1
    //   224: invokestatic b : (Landroid/content/Context;)Ljava/lang/String;
    //   227: astore #15
    //   229: aload #15
    //   231: ifnull -> 891
    //   234: aload #15
    //   236: invokevirtual length : ()I
    //   239: bipush #10
    //   241: if_icmple -> 891
    //   244: iconst_1
    //   245: istore_3
    //   246: aload #15
    //   248: astore #7
    //   250: aload #5
    //   252: astore #15
    //   254: aload #7
    //   256: astore #5
    //   258: aload #15
    //   260: astore #7
    //   262: aload #13
    //   264: ifnull -> 679
    //   267: aload #13
    //   269: arraylength
    //   270: iconst_2
    //   271: if_icmplt -> 679
    //   274: aload #13
    //   276: iconst_1
    //   277: aaload
    //   278: astore #13
    //   280: new java/lang/StringBuilder
    //   283: astore #7
    //   285: aload #7
    //   287: invokespecial <init> : ()V
    //   290: aload #7
    //   292: aload #5
    //   294: invokevirtual append : (Ljava/lang/String;)Ljava/lang/StringBuilder;
    //   297: ldc_w ','
    //   300: invokevirtual append : (Ljava/lang/String;)Ljava/lang/StringBuilder;
    //   303: aload #13
    //   305: invokevirtual append : (Ljava/lang/String;)Ljava/lang/StringBuilder;
    //   308: invokevirtual toString : ()Ljava/lang/String;
    //   311: astore #15
    //   313: iload_3
    //   314: istore #14
    //   316: new com/tencent/wxop/stat/b/c
    //   319: astore #7
    //   321: aload #7
    //   323: aload #5
    //   325: aload #13
    //   327: iload #12
    //   329: invokespecial <init> : (Ljava/lang/String;Ljava/lang/String;I)V
    //   332: aload_0
    //   333: aload #7
    //   335: putfield bY : Lcom/tencent/wxop/stat/b/c;
    //   338: new android/content/ContentValues
    //   341: astore #7
    //   343: aload #7
    //   345: invokespecial <init> : ()V
    //   348: aload #7
    //   350: ldc_w 'uid'
    //   353: aload #15
    //   355: invokestatic q : (Ljava/lang/String;)Ljava/lang/String;
    //   358: invokevirtual put : (Ljava/lang/String;Ljava/lang/String;)V
    //   361: aload #7
    //   363: ldc_w 'user_type'
    //   366: iload #12
    //   368: invokestatic valueOf : (I)Ljava/lang/Integer;
    //   371: invokevirtual put : (Ljava/lang/String;Ljava/lang/Integer;)V
    //   374: aload #7
    //   376: ldc_w 'app_ver'
    //   379: aload_1
    //   380: invokestatic G : (Landroid/content/Context;)Ljava/lang/String;
    //   383: invokevirtual put : (Ljava/lang/String;Ljava/lang/String;)V
    //   386: aload #7
    //   388: ldc_w 'ts'
    //   391: lload #10
    //   393: invokestatic valueOf : (J)Ljava/lang/Long;
    //   396: invokevirtual put : (Ljava/lang/String;Ljava/lang/Long;)V
    //   399: iload #14
    //   401: ifeq -> 432
    //   404: aload_0
    //   405: getfield bW : Lcom/tencent/wxop/stat/ac;
    //   408: invokevirtual getWritableDatabase : ()Landroid/database/sqlite/SQLiteDatabase;
    //   411: ldc_w 'user'
    //   414: aload #7
    //   416: ldc_w 'uid=?'
    //   419: iconst_1
    //   420: anewarray java/lang/String
    //   423: dup
    //   424: iconst_0
    //   425: aload #4
    //   427: aastore
    //   428: invokevirtual update : (Ljava/lang/String;Landroid/content/ContentValues;Ljava/lang/String;[Ljava/lang/String;)I
    //   431: pop
    //   432: iload #12
    //   434: iload #6
    //   436: if_icmpeq -> 456
    //   439: aload_0
    //   440: getfield bW : Lcom/tencent/wxop/stat/ac;
    //   443: invokevirtual getWritableDatabase : ()Landroid/database/sqlite/SQLiteDatabase;
    //   446: ldc_w 'user'
    //   449: aconst_null
    //   450: aload #7
    //   452: invokevirtual replace : (Ljava/lang/String;Ljava/lang/String;Landroid/content/ContentValues;)J
    //   455: pop2
    //   456: iconst_1
    //   457: istore_3
    //   458: iload_3
    //   459: ifne -> 626
    //   462: aload_1
    //   463: invokestatic c : (Landroid/content/Context;)Ljava/lang/String;
    //   466: astore #5
    //   468: aload_1
    //   469: invokestatic w : (Landroid/content/Context;)Ljava/lang/String;
    //   472: astore #15
    //   474: aload #15
    //   476: ifnull -> 884
    //   479: aload #15
    //   481: invokevirtual length : ()I
    //   484: ifle -> 884
    //   487: new java/lang/StringBuilder
    //   490: astore #7
    //   492: aload #7
    //   494: invokespecial <init> : ()V
    //   497: aload #7
    //   499: aload #5
    //   501: invokevirtual append : (Ljava/lang/String;)Ljava/lang/StringBuilder;
    //   504: ldc_w ','
    //   507: invokevirtual append : (Ljava/lang/String;)Ljava/lang/StringBuilder;
    //   510: aload #15
    //   512: invokevirtual append : (Ljava/lang/String;)Ljava/lang/StringBuilder;
    //   515: invokevirtual toString : ()Ljava/lang/String;
    //   518: astore #7
    //   520: invokestatic currentTimeMillis : ()J
    //   523: ldc2_w 1000
    //   526: ldiv
    //   527: lstore #10
    //   529: aload_1
    //   530: invokestatic G : (Landroid/content/Context;)Ljava/lang/String;
    //   533: astore_1
    //   534: new android/content/ContentValues
    //   537: astore #13
    //   539: aload #13
    //   541: invokespecial <init> : ()V
    //   544: aload #13
    //   546: ldc_w 'uid'
    //   549: aload #7
    //   551: invokestatic q : (Ljava/lang/String;)Ljava/lang/String;
    //   554: invokevirtual put : (Ljava/lang/String;Ljava/lang/String;)V
    //   557: aload #13
    //   559: ldc_w 'user_type'
    //   562: iconst_0
    //   563: invokestatic valueOf : (I)Ljava/lang/Integer;
    //   566: invokevirtual put : (Ljava/lang/String;Ljava/lang/Integer;)V
    //   569: aload #13
    //   571: ldc_w 'app_ver'
    //   574: aload_1
    //   575: invokevirtual put : (Ljava/lang/String;Ljava/lang/String;)V
    //   578: aload #13
    //   580: ldc_w 'ts'
    //   583: lload #10
    //   585: invokestatic valueOf : (J)Ljava/lang/Long;
    //   588: invokevirtual put : (Ljava/lang/String;Ljava/lang/Long;)V
    //   591: aload_0
    //   592: getfield bW : Lcom/tencent/wxop/stat/ac;
    //   595: invokevirtual getWritableDatabase : ()Landroid/database/sqlite/SQLiteDatabase;
    //   598: ldc_w 'user'
    //   601: aconst_null
    //   602: aload #13
    //   604: invokevirtual insert : (Ljava/lang/String;Ljava/lang/String;Landroid/content/ContentValues;)J
    //   607: pop2
    //   608: new com/tencent/wxop/stat/b/c
    //   611: astore_1
    //   612: aload_1
    //   613: aload #5
    //   615: aload #15
    //   617: iconst_0
    //   618: invokespecial <init> : (Ljava/lang/String;Ljava/lang/String;I)V
    //   621: aload_0
    //   622: aload_1
    //   623: putfield bY : Lcom/tencent/wxop/stat/b/c;
    //   626: aload_0
    //   627: getfield bW : Lcom/tencent/wxop/stat/ac;
    //   630: invokevirtual getWritableDatabase : ()Landroid/database/sqlite/SQLiteDatabase;
    //   633: invokevirtual setTransactionSuccessful : ()V
    //   636: aload_2
    //   637: ifnull -> 646
    //   640: aload_2
    //   641: invokeinterface close : ()V
    //   646: aload_0
    //   647: getfield bW : Lcom/tencent/wxop/stat/ac;
    //   650: invokevirtual getWritableDatabase : ()Landroid/database/sqlite/SQLiteDatabase;
    //   653: invokevirtual endTransaction : ()V
    //   656: aload_0
    //   657: getfield bY : Lcom/tencent/wxop/stat/b/c;
    //   660: astore_1
    //   661: goto -> 14
    //   664: aload_1
    //   665: invokestatic c : (Landroid/content/Context;)Ljava/lang/String;
    //   668: astore #7
    //   670: iconst_1
    //   671: istore_3
    //   672: aload #7
    //   674: astore #5
    //   676: goto -> 262
    //   679: aload_1
    //   680: invokestatic w : (Landroid/content/Context;)Ljava/lang/String;
    //   683: astore #16
    //   685: iload_3
    //   686: istore #14
    //   688: aload #16
    //   690: astore #13
    //   692: aload #7
    //   694: astore #15
    //   696: aload #16
    //   698: ifnull -> 316
    //   701: iload_3
    //   702: istore #14
    //   704: aload #16
    //   706: astore #13
    //   708: aload #7
    //   710: astore #15
    //   712: aload #16
    //   714: invokevirtual length : ()I
    //   717: ifle -> 316
    //   720: new java/lang/StringBuilder
    //   723: astore #7
    //   725: aload #7
    //   727: invokespecial <init> : ()V
    //   730: aload #7
    //   732: aload #5
    //   734: invokevirtual append : (Ljava/lang/String;)Ljava/lang/StringBuilder;
    //   737: ldc_w ','
    //   740: invokevirtual append : (Ljava/lang/String;)Ljava/lang/StringBuilder;
    //   743: aload #16
    //   745: invokevirtual append : (Ljava/lang/String;)Ljava/lang/StringBuilder;
    //   748: invokevirtual toString : ()Ljava/lang/String;
    //   751: astore #15
    //   753: iconst_1
    //   754: istore #14
    //   756: aload #16
    //   758: astore #13
    //   760: goto -> 316
    //   763: astore_1
    //   764: getstatic com/tencent/wxop/stat/t.bZ : Lcom/tencent/wxop/stat/b/b;
    //   767: aload_1
    //   768: invokevirtual b : (Ljava/lang/Throwable;)V
    //   771: goto -> 656
    //   774: astore_1
    //   775: aload_0
    //   776: monitorexit
    //   777: aload_1
    //   778: athrow
    //   779: astore #7
    //   781: aconst_null
    //   782: astore_1
    //   783: getstatic com/tencent/wxop/stat/t.bZ : Lcom/tencent/wxop/stat/b/b;
    //   786: aload #7
    //   788: invokevirtual b : (Ljava/lang/Throwable;)V
    //   791: aload_1
    //   792: ifnull -> 801
    //   795: aload_1
    //   796: invokeinterface close : ()V
    //   801: aload_0
    //   802: getfield bW : Lcom/tencent/wxop/stat/ac;
    //   805: invokevirtual getWritableDatabase : ()Landroid/database/sqlite/SQLiteDatabase;
    //   808: invokevirtual endTransaction : ()V
    //   811: goto -> 656
    //   814: astore_1
    //   815: getstatic com/tencent/wxop/stat/t.bZ : Lcom/tencent/wxop/stat/b/b;
    //   818: aload_1
    //   819: invokevirtual b : (Ljava/lang/Throwable;)V
    //   822: goto -> 656
    //   825: astore_1
    //   826: aconst_null
    //   827: astore_2
    //   828: aload_2
    //   829: ifnull -> 838
    //   832: aload_2
    //   833: invokeinterface close : ()V
    //   838: aload_0
    //   839: getfield bW : Lcom/tencent/wxop/stat/ac;
    //   842: invokevirtual getWritableDatabase : ()Landroid/database/sqlite/SQLiteDatabase;
    //   845: invokevirtual endTransaction : ()V
    //   848: aload_1
    //   849: athrow
    //   850: astore #7
    //   852: getstatic com/tencent/wxop/stat/t.bZ : Lcom/tencent/wxop/stat/b/b;
    //   855: aload #7
    //   857: invokevirtual b : (Ljava/lang/Throwable;)V
    //   860: goto -> 848
    //   863: astore_1
    //   864: goto -> 828
    //   867: astore #7
    //   869: aload_1
    //   870: astore_2
    //   871: aload #7
    //   873: astore_1
    //   874: goto -> 828
    //   877: astore #7
    //   879: aload_2
    //   880: astore_1
    //   881: goto -> 783
    //   884: aload #5
    //   886: astore #7
    //   888: goto -> 520
    //   891: goto -> 250
    //   894: aload #5
    //   896: astore #15
    //   898: aload #7
    //   900: astore #5
    //   902: iload #14
    //   904: istore_3
    //   905: aload #15
    //   907: astore #7
    //   909: goto -> 262
    //   912: iload_3
    //   913: istore #12
    //   915: goto -> 176
    //   918: iload #6
    //   920: istore_3
    //   921: goto -> 159
    // Exception table:
    //   from	to	target	type
    //   2	14	774	finally
    //   18	43	779	java/lang/Throwable
    //   18	43	825	finally
    //   43	64	779	java/lang/Throwable
    //   43	64	825	finally
    //   66	127	877	java/lang/Throwable
    //   66	127	863	finally
    //   133	157	877	java/lang/Throwable
    //   133	157	863	finally
    //   159	171	877	java/lang/Throwable
    //   159	171	863	finally
    //   176	186	877	java/lang/Throwable
    //   176	186	863	finally
    //   196	202	877	java/lang/Throwable
    //   196	202	863	finally
    //   213	223	877	java/lang/Throwable
    //   213	223	863	finally
    //   223	229	877	java/lang/Throwable
    //   223	229	863	finally
    //   234	244	877	java/lang/Throwable
    //   234	244	863	finally
    //   267	274	877	java/lang/Throwable
    //   267	274	863	finally
    //   280	313	877	java/lang/Throwable
    //   280	313	863	finally
    //   316	399	877	java/lang/Throwable
    //   316	399	863	finally
    //   404	432	877	java/lang/Throwable
    //   404	432	863	finally
    //   439	456	877	java/lang/Throwable
    //   439	456	863	finally
    //   462	474	877	java/lang/Throwable
    //   462	474	863	finally
    //   479	520	877	java/lang/Throwable
    //   479	520	863	finally
    //   520	626	877	java/lang/Throwable
    //   520	626	863	finally
    //   626	636	877	java/lang/Throwable
    //   626	636	863	finally
    //   640	646	763	java/lang/Throwable
    //   640	646	774	finally
    //   646	656	763	java/lang/Throwable
    //   646	656	774	finally
    //   656	661	774	finally
    //   664	670	877	java/lang/Throwable
    //   664	670	863	finally
    //   679	685	877	java/lang/Throwable
    //   679	685	863	finally
    //   712	753	877	java/lang/Throwable
    //   712	753	863	finally
    //   764	771	774	finally
    //   783	791	867	finally
    //   795	801	814	java/lang/Throwable
    //   795	801	774	finally
    //   801	811	814	java/lang/Throwable
    //   801	811	774	finally
    //   815	822	774	finally
    //   832	838	850	java/lang/Throwable
    //   832	838	774	finally
    //   838	848	850	java/lang/Throwable
    //   838	848	774	finally
    //   848	850	774	finally
    //   852	860	774	finally
  }
}


/* Location:              D:\Code\Crack\dex-tools-2.1-20190905-lanchon\zspns-pcgw-P36417A-0429-dex2jar.jar!\com\tencent\wxop\stat\t.class
 * Java compiler version: 6 (50.0)
 * JD-Core Version:       1.1.3
 */