package com.unionpay.mobile.android.utils;

final class n extends Thread {
  n(l paraml) {}
  
  public final void run() {
    // Byte code:
    //   0: aload_0
    //   1: invokespecial run : ()V
    //   4: aload_0
    //   5: monitorenter
    //   6: aload_0
    //   7: ldc2_w 1000
    //   10: invokevirtual wait : (J)V
    //   13: aload_0
    //   14: monitorexit
    //   15: aload_0
    //   16: getfield a : Lcom/unionpay/mobile/android/utils/l;
    //   19: astore_1
    //   20: aload_1
    //   21: monitorenter
    //   22: invokestatic b : ()Lorg/simalliance/openmobileapi/SEService;
    //   25: ifnull -> 37
    //   28: invokestatic b : ()Lorg/simalliance/openmobileapi/SEService;
    //   31: invokevirtual isConnected : ()Z
    //   34: ifne -> 67
    //   37: ldc 'uppay'
    //   39: ldc 'se service connection time out'
    //   41: invokestatic c : (Ljava/lang/String;Ljava/lang/String;)I
    //   44: pop
    //   45: aload_0
    //   46: getfield a : Lcom/unionpay/mobile/android/utils/l;
    //   49: invokestatic b : (Lcom/unionpay/mobile/android/utils/l;)Landroid/os/Handler;
    //   52: ifnull -> 67
    //   55: aload_0
    //   56: getfield a : Lcom/unionpay/mobile/android/utils/l;
    //   59: invokestatic b : (Lcom/unionpay/mobile/android/utils/l;)Landroid/os/Handler;
    //   62: iconst_2
    //   63: invokevirtual sendEmptyMessage : (I)Z
    //   66: pop
    //   67: aload_1
    //   68: monitorexit
    //   69: return
    //   70: astore_2
    //   71: aload_0
    //   72: monitorexit
    //   73: aload_2
    //   74: athrow
    //   75: astore_2
    //   76: aload_2
    //   77: invokevirtual printStackTrace : ()V
    //   80: ldc 'uppay'
    //   82: new java/lang/StringBuilder
    //   85: dup
    //   86: invokespecial <init> : ()V
    //   89: aload_2
    //   90: invokevirtual getMessage : ()Ljava/lang/String;
    //   93: invokevirtual append : (Ljava/lang/String;)Ljava/lang/StringBuilder;
    //   96: invokevirtual toString : ()Ljava/lang/String;
    //   99: invokestatic c : (Ljava/lang/String;Ljava/lang/String;)I
    //   102: pop
    //   103: goto -> 15
    //   106: astore_2
    //   107: aload_1
    //   108: monitorexit
    //   109: aload_2
    //   110: athrow
    // Exception table:
    //   from	to	target	type
    //   4	6	75	java/lang/InterruptedException
    //   6	15	70	finally
    //   22	37	106	finally
    //   37	67	106	finally
    //   67	69	106	finally
    //   71	75	75	java/lang/InterruptedException
  }
}


/* Location:              D:\Code\Crack\dex-tools-2.1-20190905-lanchon\zspns-pcgw-P36417A-0429-dex2jar.jar!\co\\unionpay\mobile\androi\\utils\n.class
 * Java compiler version: 6 (50.0)
 * JD-Core Version:       1.1.3
 */