package com.zz.sdk.i;

import android.content.Context;
import android.location.Location;

public class bo {
  public static Location a(Context paramContext) {
    // Byte code:
    //   0: aconst_null
    //   1: astore_1
    //   2: aload_0
    //   3: invokestatic d : (Landroid/content/Context;)Z
    //   6: ifne -> 13
    //   9: aconst_null
    //   10: astore_0
    //   11: aload_0
    //   12: areturn
    //   13: new android/location/Location
    //   16: dup
    //   17: ldc 'network'
    //   19: invokespecial <init> : (Ljava/lang/String;)V
    //   22: astore_2
    //   23: aload_0
    //   24: ldc 'phone'
    //   26: invokevirtual getSystemService : (Ljava/lang/String;)Ljava/lang/Object;
    //   29: checkcast android/telephony/TelephonyManager
    //   32: astore_0
    //   33: aload_0
    //   34: invokevirtual getCellLocation : ()Landroid/telephony/CellLocation;
    //   37: astore_3
    //   38: aload_3
    //   39: ifnonnull -> 68
    //   42: iconst_0
    //   43: ifeq -> 54
    //   46: new java/lang/NullPointerException
    //   49: dup
    //   50: invokespecial <init> : ()V
    //   53: athrow
    //   54: aconst_null
    //   55: astore_0
    //   56: goto -> 11
    //   59: astore_0
    //   60: ldc 'network get the latitude and longitude when closed BufferedReader ocurr IOException error'
    //   62: invokestatic a : (Ljava/lang/Object;)V
    //   65: goto -> 54
    //   68: aload_3
    //   69: instanceof android/telephony/gsm/GsmCellLocation
    //   72: ifeq -> 511
    //   75: aload_3
    //   76: checkcast android/telephony/gsm/GsmCellLocation
    //   79: astore_3
    //   80: aload_3
    //   81: invokevirtual getCid : ()I
    //   84: istore #4
    //   86: aload_3
    //   87: invokevirtual getLac : ()I
    //   90: istore #5
    //   92: aload_0
    //   93: invokevirtual getNetworkOperator : ()Ljava/lang/String;
    //   96: iconst_0
    //   97: iconst_3
    //   98: invokevirtual substring : (II)Ljava/lang/String;
    //   101: invokestatic valueOf : (Ljava/lang/String;)Ljava/lang/Integer;
    //   104: invokevirtual intValue : ()I
    //   107: istore #6
    //   109: aload_0
    //   110: invokevirtual getNetworkOperator : ()Ljava/lang/String;
    //   113: iconst_3
    //   114: iconst_5
    //   115: invokevirtual substring : (II)Ljava/lang/String;
    //   118: invokestatic valueOf : (Ljava/lang/String;)Ljava/lang/Integer;
    //   121: invokevirtual intValue : ()I
    //   124: istore #7
    //   126: new org/json/JSONObject
    //   129: astore_0
    //   130: aload_0
    //   131: invokespecial <init> : ()V
    //   134: aload_0
    //   135: ldc 'version'
    //   137: ldc '1.1.0'
    //   139: invokevirtual put : (Ljava/lang/String;Ljava/lang/Object;)Lorg/json/JSONObject;
    //   142: pop
    //   143: aload_0
    //   144: ldc 'host'
    //   146: ldc 'maps.google.com'
    //   148: invokevirtual put : (Ljava/lang/String;Ljava/lang/Object;)Lorg/json/JSONObject;
    //   151: pop
    //   152: aload_0
    //   153: ldc 'request_address'
    //   155: iconst_1
    //   156: invokevirtual put : (Ljava/lang/String;Z)Lorg/json/JSONObject;
    //   159: pop
    //   160: new org/json/JSONArray
    //   163: astore_3
    //   164: aload_3
    //   165: invokespecial <init> : ()V
    //   168: new org/json/JSONObject
    //   171: astore #8
    //   173: aload #8
    //   175: invokespecial <init> : ()V
    //   178: aload #8
    //   180: ldc 'cell_id'
    //   182: iload #4
    //   184: invokevirtual put : (Ljava/lang/String;I)Lorg/json/JSONObject;
    //   187: pop
    //   188: aload #8
    //   190: ldc 'location_area_code'
    //   192: iload #5
    //   194: invokevirtual put : (Ljava/lang/String;I)Lorg/json/JSONObject;
    //   197: pop
    //   198: aload #8
    //   200: ldc 'mobile_country_code'
    //   202: iload #6
    //   204: invokevirtual put : (Ljava/lang/String;I)Lorg/json/JSONObject;
    //   207: pop
    //   208: aload #8
    //   210: ldc 'mobile_network_code'
    //   212: iload #7
    //   214: invokevirtual put : (Ljava/lang/String;I)Lorg/json/JSONObject;
    //   217: pop
    //   218: aload_3
    //   219: aload #8
    //   221: invokevirtual put : (Ljava/lang/Object;)Lorg/json/JSONArray;
    //   224: pop
    //   225: aload_0
    //   226: ldc 'cell_towers'
    //   228: aload_3
    //   229: invokevirtual put : (Ljava/lang/String;Ljava/lang/Object;)Lorg/json/JSONObject;
    //   232: pop
    //   233: new org/apache/http/impl/client/DefaultHttpClient
    //   236: astore_3
    //   237: aload_3
    //   238: invokespecial <init> : ()V
    //   241: aload_3
    //   242: invokevirtual getParams : ()Lorg/apache/http/params/HttpParams;
    //   245: ldc 'http.connection.timeout'
    //   247: sipush #15000
    //   250: invokestatic valueOf : (I)Ljava/lang/Integer;
    //   253: invokeinterface setParameter : (Ljava/lang/String;Ljava/lang/Object;)Lorg/apache/http/params/HttpParams;
    //   258: pop
    //   259: aload_3
    //   260: invokevirtual getParams : ()Lorg/apache/http/params/HttpParams;
    //   263: ldc 'http.socket.timeout'
    //   265: sipush #15000
    //   268: invokestatic valueOf : (I)Ljava/lang/Integer;
    //   271: invokeinterface setParameter : (Ljava/lang/String;Ljava/lang/Object;)Lorg/apache/http/params/HttpParams;
    //   276: pop
    //   277: new org/apache/http/client/methods/HttpPost
    //   280: astore #9
    //   282: aload #9
    //   284: ldc 'http://www.google.com/loc/json'
    //   286: invokespecial <init> : (Ljava/lang/String;)V
    //   289: new org/apache/http/entity/StringEntity
    //   292: astore #8
    //   294: aload #8
    //   296: aload_0
    //   297: invokevirtual toString : ()Ljava/lang/String;
    //   300: invokespecial <init> : (Ljava/lang/String;)V
    //   303: aload #9
    //   305: aload #8
    //   307: invokevirtual setEntity : (Lorg/apache/http/HttpEntity;)V
    //   310: aload_3
    //   311: aload #9
    //   313: invokevirtual execute : (Lorg/apache/http/client/methods/HttpUriRequest;)Lorg/apache/http/HttpResponse;
    //   316: astore_0
    //   317: aload_0
    //   318: invokeinterface getStatusLine : ()Lorg/apache/http/StatusLine;
    //   323: invokeinterface getStatusCode : ()I
    //   328: sipush #200
    //   331: if_icmpne -> 583
    //   334: aload_0
    //   335: invokeinterface getEntity : ()Lorg/apache/http/HttpEntity;
    //   340: astore #8
    //   342: new java/io/BufferedReader
    //   345: astore_0
    //   346: new java/io/InputStreamReader
    //   349: astore_3
    //   350: aload_3
    //   351: aload #8
    //   353: invokeinterface getContent : ()Ljava/io/InputStream;
    //   358: invokespecial <init> : (Ljava/io/InputStream;)V
    //   361: aload_0
    //   362: aload_3
    //   363: invokespecial <init> : (Ljava/io/Reader;)V
    //   366: aload_0
    //   367: astore_1
    //   368: new java/lang/StringBuffer
    //   371: astore_3
    //   372: aload_0
    //   373: astore_1
    //   374: aload_3
    //   375: invokespecial <init> : ()V
    //   378: aload_0
    //   379: astore_1
    //   380: aload_0
    //   381: invokevirtual readLine : ()Ljava/lang/String;
    //   384: astore #8
    //   386: aload #8
    //   388: ifnull -> 422
    //   391: aload_0
    //   392: astore_1
    //   393: aload_3
    //   394: aload #8
    //   396: invokevirtual append : (Ljava/lang/String;)Ljava/lang/StringBuffer;
    //   399: pop
    //   400: goto -> 378
    //   403: astore_1
    //   404: ldc 'network get the latitude and longitude ocurr JSONException error'
    //   406: invokestatic a : (Ljava/lang/Object;)V
    //   409: aload_0
    //   410: ifnull -> 417
    //   413: aload_0
    //   414: invokevirtual close : ()V
    //   417: aconst_null
    //   418: astore_0
    //   419: goto -> 11
    //   422: aload_0
    //   423: astore_1
    //   424: new org/json/JSONObject
    //   427: astore #8
    //   429: aload_0
    //   430: astore_1
    //   431: aload #8
    //   433: aload_3
    //   434: invokevirtual toString : ()Ljava/lang/String;
    //   437: invokespecial <init> : (Ljava/lang/String;)V
    //   440: aload_0
    //   441: astore_1
    //   442: aload #8
    //   444: ldc 'location'
    //   446: invokevirtual get : (Ljava/lang/String;)Ljava/lang/Object;
    //   449: checkcast org/json/JSONObject
    //   452: astore_3
    //   453: aload_0
    //   454: astore_1
    //   455: aload_2
    //   456: aload_3
    //   457: ldc 'latitude'
    //   459: invokevirtual get : (Ljava/lang/String;)Ljava/lang/Object;
    //   462: checkcast java/lang/Double
    //   465: invokevirtual doubleValue : ()D
    //   468: invokevirtual setLatitude : (D)V
    //   471: aload_0
    //   472: astore_1
    //   473: aload_2
    //   474: aload_3
    //   475: ldc 'longitude'
    //   477: invokevirtual get : (Ljava/lang/String;)Ljava/lang/Object;
    //   480: checkcast java/lang/Double
    //   483: invokevirtual doubleValue : ()D
    //   486: invokevirtual setLongitude : (D)V
    //   489: aload_0
    //   490: ifnull -> 497
    //   493: aload_0
    //   494: invokevirtual close : ()V
    //   497: aload_2
    //   498: astore_0
    //   499: goto -> 11
    //   502: astore_0
    //   503: ldc 'network get the latitude and longitude when closed BufferedReader ocurr IOException error'
    //   505: invokestatic a : (Ljava/lang/Object;)V
    //   508: goto -> 497
    //   511: aload_3
    //   512: instanceof android/telephony/cdma/CdmaCellLocation
    //   515: ifeq -> 583
    //   518: aload_3
    //   519: checkcast android/telephony/cdma/CdmaCellLocation
    //   522: astore_0
    //   523: aload_0
    //   524: invokevirtual getBaseStationLongitude : ()I
    //   527: istore #7
    //   529: aload_0
    //   530: invokevirtual getBaseStationLatitude : ()I
    //   533: istore #5
    //   535: aload_2
    //   536: iload #7
    //   538: i2d
    //   539: ldc2_w 14400.0
    //   542: ddiv
    //   543: invokevirtual setLongitude : (D)V
    //   546: aload_2
    //   547: iload #5
    //   549: i2d
    //   550: ldc2_w 14400.0
    //   553: ddiv
    //   554: invokevirtual setLatitude : (D)V
    //   557: iconst_0
    //   558: ifeq -> 569
    //   561: new java/lang/NullPointerException
    //   564: dup
    //   565: invokespecial <init> : ()V
    //   568: athrow
    //   569: aload_2
    //   570: astore_0
    //   571: goto -> 11
    //   574: astore_0
    //   575: ldc 'network get the latitude and longitude when closed BufferedReader ocurr IOException error'
    //   577: invokestatic a : (Ljava/lang/Object;)V
    //   580: goto -> 569
    //   583: iconst_0
    //   584: ifeq -> 595
    //   587: new java/lang/NullPointerException
    //   590: dup
    //   591: invokespecial <init> : ()V
    //   594: athrow
    //   595: aconst_null
    //   596: astore_0
    //   597: goto -> 11
    //   600: astore_0
    //   601: ldc 'network get the latitude and longitude when closed BufferedReader ocurr IOException error'
    //   603: invokestatic a : (Ljava/lang/Object;)V
    //   606: goto -> 595
    //   609: astore_0
    //   610: ldc 'network get the latitude and longitude when closed BufferedReader ocurr IOException error'
    //   612: invokestatic a : (Ljava/lang/Object;)V
    //   615: goto -> 417
    //   618: astore_0
    //   619: aconst_null
    //   620: astore_0
    //   621: aload_0
    //   622: astore_1
    //   623: ldc 'network get the latitude and longitude ocurr ClientProtocolException error'
    //   625: invokestatic a : (Ljava/lang/Object;)V
    //   628: aload_0
    //   629: ifnull -> 417
    //   632: aload_0
    //   633: invokevirtual close : ()V
    //   636: goto -> 417
    //   639: astore_0
    //   640: ldc 'network get the latitude and longitude when closed BufferedReader ocurr IOException error'
    //   642: invokestatic a : (Ljava/lang/Object;)V
    //   645: goto -> 417
    //   648: astore_0
    //   649: aconst_null
    //   650: astore_0
    //   651: aload_0
    //   652: astore_1
    //   653: ldc 'network get the latitude and longitude ocurr IOException error'
    //   655: invokestatic a : (Ljava/lang/Object;)V
    //   658: aload_0
    //   659: ifnull -> 417
    //   662: aload_0
    //   663: invokevirtual close : ()V
    //   666: goto -> 417
    //   669: astore_0
    //   670: ldc 'network get the latitude and longitude when closed BufferedReader ocurr IOException error'
    //   672: invokestatic a : (Ljava/lang/Object;)V
    //   675: goto -> 417
    //   678: astore_0
    //   679: aconst_null
    //   680: astore_0
    //   681: aload_0
    //   682: astore_1
    //   683: ldc 'network get the latitude and longitude ocurr Exception error'
    //   685: invokestatic a : (Ljava/lang/Object;)V
    //   688: aload_0
    //   689: ifnull -> 417
    //   692: aload_0
    //   693: invokevirtual close : ()V
    //   696: goto -> 417
    //   699: astore_0
    //   700: ldc 'network get the latitude and longitude when closed BufferedReader ocurr IOException error'
    //   702: invokestatic a : (Ljava/lang/Object;)V
    //   705: goto -> 417
    //   708: astore_0
    //   709: aload_1
    //   710: ifnull -> 717
    //   713: aload_1
    //   714: invokevirtual close : ()V
    //   717: aload_0
    //   718: athrow
    //   719: astore_1
    //   720: ldc 'network get the latitude and longitude when closed BufferedReader ocurr IOException error'
    //   722: invokestatic a : (Ljava/lang/Object;)V
    //   725: goto -> 717
    //   728: astore_0
    //   729: goto -> 709
    //   732: astore_2
    //   733: aload_0
    //   734: astore_1
    //   735: aload_2
    //   736: astore_0
    //   737: goto -> 709
    //   740: astore_1
    //   741: goto -> 681
    //   744: astore_1
    //   745: goto -> 651
    //   748: astore_1
    //   749: goto -> 621
    //   752: astore_0
    //   753: aconst_null
    //   754: astore_0
    //   755: goto -> 404
    // Exception table:
    //   from	to	target	type
    //   33	38	752	org/json/JSONException
    //   33	38	618	org/apache/http/client/ClientProtocolException
    //   33	38	648	java/io/IOException
    //   33	38	678	java/lang/Exception
    //   33	38	708	finally
    //   46	54	59	java/io/IOException
    //   68	366	752	org/json/JSONException
    //   68	366	618	org/apache/http/client/ClientProtocolException
    //   68	366	648	java/io/IOException
    //   68	366	678	java/lang/Exception
    //   68	366	708	finally
    //   368	372	403	org/json/JSONException
    //   368	372	748	org/apache/http/client/ClientProtocolException
    //   368	372	744	java/io/IOException
    //   368	372	740	java/lang/Exception
    //   368	372	728	finally
    //   374	378	403	org/json/JSONException
    //   374	378	748	org/apache/http/client/ClientProtocolException
    //   374	378	744	java/io/IOException
    //   374	378	740	java/lang/Exception
    //   374	378	728	finally
    //   380	386	403	org/json/JSONException
    //   380	386	748	org/apache/http/client/ClientProtocolException
    //   380	386	744	java/io/IOException
    //   380	386	740	java/lang/Exception
    //   380	386	728	finally
    //   393	400	403	org/json/JSONException
    //   393	400	748	org/apache/http/client/ClientProtocolException
    //   393	400	744	java/io/IOException
    //   393	400	740	java/lang/Exception
    //   393	400	728	finally
    //   404	409	732	finally
    //   413	417	609	java/io/IOException
    //   424	429	403	org/json/JSONException
    //   424	429	748	org/apache/http/client/ClientProtocolException
    //   424	429	744	java/io/IOException
    //   424	429	740	java/lang/Exception
    //   424	429	728	finally
    //   431	440	403	org/json/JSONException
    //   431	440	748	org/apache/http/client/ClientProtocolException
    //   431	440	744	java/io/IOException
    //   431	440	740	java/lang/Exception
    //   431	440	728	finally
    //   442	453	403	org/json/JSONException
    //   442	453	748	org/apache/http/client/ClientProtocolException
    //   442	453	744	java/io/IOException
    //   442	453	740	java/lang/Exception
    //   442	453	728	finally
    //   455	471	403	org/json/JSONException
    //   455	471	748	org/apache/http/client/ClientProtocolException
    //   455	471	744	java/io/IOException
    //   455	471	740	java/lang/Exception
    //   455	471	728	finally
    //   473	489	403	org/json/JSONException
    //   473	489	748	org/apache/http/client/ClientProtocolException
    //   473	489	744	java/io/IOException
    //   473	489	740	java/lang/Exception
    //   473	489	728	finally
    //   493	497	502	java/io/IOException
    //   511	557	752	org/json/JSONException
    //   511	557	618	org/apache/http/client/ClientProtocolException
    //   511	557	648	java/io/IOException
    //   511	557	678	java/lang/Exception
    //   511	557	708	finally
    //   561	569	574	java/io/IOException
    //   587	595	600	java/io/IOException
    //   623	628	728	finally
    //   632	636	639	java/io/IOException
    //   653	658	728	finally
    //   662	666	669	java/io/IOException
    //   683	688	728	finally
    //   692	696	699	java/io/IOException
    //   713	717	719	java/io/IOException
  }
  
  public static String a(double paramDouble1, double paramDouble2) {
    // Byte code:
    //   0: ldc 'http://ugc.map.soso.com/rgeoc/?lnglat=%s,%s&reqsrc=wb'
    //   2: iconst_2
    //   3: anewarray java/lang/Object
    //   6: dup
    //   7: iconst_0
    //   8: dload_0
    //   9: invokestatic valueOf : (D)Ljava/lang/Double;
    //   12: aastore
    //   13: dup
    //   14: iconst_1
    //   15: dload_2
    //   16: invokestatic valueOf : (D)Ljava/lang/Double;
    //   19: aastore
    //   20: invokestatic format : (Ljava/lang/String;[Ljava/lang/Object;)Ljava/lang/String;
    //   23: astore #4
    //   25: sipush #1024
    //   28: newarray byte
    //   30: astore #5
    //   32: new java/net/URL
    //   35: astore #6
    //   37: aload #6
    //   39: aload #4
    //   41: invokespecial <init> : (Ljava/lang/String;)V
    //   44: aload #6
    //   46: invokevirtual openConnection : ()Ljava/net/URLConnection;
    //   49: checkcast java/net/HttpURLConnection
    //   52: astore #6
    //   54: aload #6
    //   56: sipush #10000
    //   59: invokevirtual setReadTimeout : (I)V
    //   62: aload #6
    //   64: sipush #10000
    //   67: invokevirtual setConnectTimeout : (I)V
    //   70: aload #6
    //   72: invokevirtual getInputStream : ()Ljava/io/InputStream;
    //   75: astore #6
    //   77: new java/io/ByteArrayOutputStream
    //   80: astore #7
    //   82: aload #7
    //   84: invokespecial <init> : ()V
    //   87: aload #7
    //   89: astore #8
    //   91: aload #6
    //   93: astore #4
    //   95: aload #6
    //   97: aload #5
    //   99: invokevirtual read : ([B)I
    //   102: istore #9
    //   104: iload #9
    //   106: iconst_m1
    //   107: if_icmpeq -> 172
    //   110: aload #7
    //   112: astore #8
    //   114: aload #6
    //   116: astore #4
    //   118: aload #7
    //   120: aload #5
    //   122: iconst_0
    //   123: iload #9
    //   125: invokevirtual write : ([BII)V
    //   128: goto -> 87
    //   131: astore #5
    //   133: aload #7
    //   135: astore #8
    //   137: aload #6
    //   139: astore #4
    //   141: aload #5
    //   143: invokevirtual printStackTrace : ()V
    //   146: aload #6
    //   148: ifnull -> 156
    //   151: aload #6
    //   153: invokevirtual close : ()V
    //   156: aload #7
    //   158: ifnull -> 166
    //   161: aload #7
    //   163: invokevirtual close : ()V
    //   166: aconst_null
    //   167: astore #6
    //   169: aload #6
    //   171: areturn
    //   172: aload #7
    //   174: astore #8
    //   176: aload #6
    //   178: astore #4
    //   180: new java/lang/String
    //   183: astore #5
    //   185: aload #7
    //   187: astore #8
    //   189: aload #6
    //   191: astore #4
    //   193: aload #5
    //   195: aload #7
    //   197: invokevirtual toByteArray : ()[B
    //   200: ldc_w 'gbk'
    //   203: invokespecial <init> : ([BLjava/lang/String;)V
    //   206: aload #7
    //   208: astore #8
    //   210: aload #6
    //   212: astore #4
    //   214: new org/json/JSONObject
    //   217: astore #10
    //   219: aload #7
    //   221: astore #8
    //   223: aload #6
    //   225: astore #4
    //   227: aload #10
    //   229: aload #5
    //   231: invokespecial <init> : (Ljava/lang/String;)V
    //   234: aload #7
    //   236: astore #8
    //   238: aload #6
    //   240: astore #4
    //   242: aload #10
    //   244: ldc_w 'detail'
    //   247: invokevirtual getJSONObject : (Ljava/lang/String;)Lorg/json/JSONObject;
    //   250: ldc_w 'results'
    //   253: invokevirtual getJSONArray : (Ljava/lang/String;)Lorg/json/JSONArray;
    //   256: astore #10
    //   258: iconst_0
    //   259: istore #9
    //   261: aload #7
    //   263: astore #8
    //   265: aload #6
    //   267: astore #4
    //   269: iload #9
    //   271: aload #10
    //   273: invokevirtual length : ()I
    //   276: if_icmpge -> 404
    //   279: aload #7
    //   281: astore #8
    //   283: aload #6
    //   285: astore #4
    //   287: aload #10
    //   289: iload #9
    //   291: invokevirtual getJSONObject : (I)Lorg/json/JSONObject;
    //   294: astore #5
    //   296: aload #7
    //   298: astore #8
    //   300: aload #6
    //   302: astore #4
    //   304: ldc_w 'AD'
    //   307: aload #5
    //   309: ldc_w 'dtype'
    //   312: invokevirtual getString : (Ljava/lang/String;)Ljava/lang/String;
    //   315: invokevirtual equals : (Ljava/lang/Object;)Z
    //   318: ifeq -> 398
    //   321: aload #7
    //   323: astore #8
    //   325: aload #6
    //   327: astore #4
    //   329: aload #5
    //   331: ldc_w 'name'
    //   334: invokevirtual getString : (Ljava/lang/String;)Ljava/lang/String;
    //   337: astore #5
    //   339: aload #5
    //   341: astore #4
    //   343: aload #6
    //   345: ifnull -> 353
    //   348: aload #6
    //   350: invokevirtual close : ()V
    //   353: aload #4
    //   355: astore #6
    //   357: aload #7
    //   359: ifnull -> 169
    //   362: aload #7
    //   364: invokevirtual close : ()V
    //   367: aload #4
    //   369: astore #6
    //   371: goto -> 169
    //   374: astore #6
    //   376: aload #6
    //   378: invokevirtual printStackTrace : ()V
    //   381: aload #4
    //   383: astore #6
    //   385: goto -> 169
    //   388: astore #6
    //   390: aload #6
    //   392: invokevirtual printStackTrace : ()V
    //   395: goto -> 353
    //   398: iinc #9, 1
    //   401: goto -> 261
    //   404: aload #6
    //   406: ifnull -> 414
    //   409: aload #6
    //   411: invokevirtual close : ()V
    //   414: aload #7
    //   416: ifnull -> 166
    //   419: aload #7
    //   421: invokevirtual close : ()V
    //   424: goto -> 166
    //   427: astore #6
    //   429: aload #6
    //   431: invokevirtual printStackTrace : ()V
    //   434: goto -> 166
    //   437: astore #6
    //   439: aload #6
    //   441: invokevirtual printStackTrace : ()V
    //   444: goto -> 414
    //   447: astore #6
    //   449: aload #6
    //   451: invokevirtual printStackTrace : ()V
    //   454: goto -> 156
    //   457: astore #6
    //   459: aload #6
    //   461: invokevirtual printStackTrace : ()V
    //   464: goto -> 166
    //   467: astore #5
    //   469: aconst_null
    //   470: astore #7
    //   472: aconst_null
    //   473: astore #6
    //   475: aload #7
    //   477: astore #8
    //   479: aload #6
    //   481: astore #4
    //   483: aload #5
    //   485: invokevirtual printStackTrace : ()V
    //   488: aload #6
    //   490: ifnull -> 498
    //   493: aload #6
    //   495: invokevirtual close : ()V
    //   498: aload #7
    //   500: ifnull -> 166
    //   503: aload #7
    //   505: invokevirtual close : ()V
    //   508: goto -> 166
    //   511: astore #6
    //   513: aload #6
    //   515: invokevirtual printStackTrace : ()V
    //   518: goto -> 166
    //   521: astore #6
    //   523: aload #6
    //   525: invokevirtual printStackTrace : ()V
    //   528: goto -> 498
    //   531: astore #5
    //   533: aconst_null
    //   534: astore #7
    //   536: aconst_null
    //   537: astore #6
    //   539: aload #7
    //   541: astore #8
    //   543: aload #6
    //   545: astore #4
    //   547: aload #5
    //   549: invokevirtual printStackTrace : ()V
    //   552: aload #6
    //   554: ifnull -> 562
    //   557: aload #6
    //   559: invokevirtual close : ()V
    //   562: aload #7
    //   564: ifnull -> 166
    //   567: aload #7
    //   569: invokevirtual close : ()V
    //   572: goto -> 166
    //   575: astore #6
    //   577: aload #6
    //   579: invokevirtual printStackTrace : ()V
    //   582: goto -> 166
    //   585: astore #6
    //   587: aload #6
    //   589: invokevirtual printStackTrace : ()V
    //   592: goto -> 562
    //   595: astore #7
    //   597: aconst_null
    //   598: astore #8
    //   600: aconst_null
    //   601: astore #6
    //   603: aload #6
    //   605: ifnull -> 613
    //   608: aload #6
    //   610: invokevirtual close : ()V
    //   613: aload #8
    //   615: ifnull -> 623
    //   618: aload #8
    //   620: invokevirtual close : ()V
    //   623: aload #7
    //   625: athrow
    //   626: astore #6
    //   628: aload #6
    //   630: invokevirtual printStackTrace : ()V
    //   633: goto -> 613
    //   636: astore #6
    //   638: aload #6
    //   640: invokevirtual printStackTrace : ()V
    //   643: goto -> 623
    //   646: astore #7
    //   648: aconst_null
    //   649: astore #8
    //   651: goto -> 603
    //   654: astore #7
    //   656: aload #4
    //   658: astore #6
    //   660: goto -> 603
    //   663: astore #5
    //   665: aconst_null
    //   666: astore #7
    //   668: goto -> 539
    //   671: astore #5
    //   673: goto -> 539
    //   676: astore #5
    //   678: aconst_null
    //   679: astore #7
    //   681: goto -> 475
    //   684: astore #5
    //   686: goto -> 475
    //   689: astore #5
    //   691: aconst_null
    //   692: astore #7
    //   694: aconst_null
    //   695: astore #6
    //   697: goto -> 133
    //   700: astore #5
    //   702: aconst_null
    //   703: astore #7
    //   705: goto -> 133
    // Exception table:
    //   from	to	target	type
    //   32	77	689	java/io/IOException
    //   32	77	467	org/json/JSONException
    //   32	77	531	java/lang/Exception
    //   32	77	595	finally
    //   77	87	700	java/io/IOException
    //   77	87	676	org/json/JSONException
    //   77	87	663	java/lang/Exception
    //   77	87	646	finally
    //   95	104	131	java/io/IOException
    //   95	104	684	org/json/JSONException
    //   95	104	671	java/lang/Exception
    //   95	104	654	finally
    //   118	128	131	java/io/IOException
    //   118	128	684	org/json/JSONException
    //   118	128	671	java/lang/Exception
    //   118	128	654	finally
    //   141	146	654	finally
    //   151	156	447	java/io/IOException
    //   161	166	457	java/io/IOException
    //   180	185	131	java/io/IOException
    //   180	185	684	org/json/JSONException
    //   180	185	671	java/lang/Exception
    //   180	185	654	finally
    //   193	206	131	java/io/IOException
    //   193	206	684	org/json/JSONException
    //   193	206	671	java/lang/Exception
    //   193	206	654	finally
    //   214	219	131	java/io/IOException
    //   214	219	684	org/json/JSONException
    //   214	219	671	java/lang/Exception
    //   214	219	654	finally
    //   227	234	131	java/io/IOException
    //   227	234	684	org/json/JSONException
    //   227	234	671	java/lang/Exception
    //   227	234	654	finally
    //   242	258	131	java/io/IOException
    //   242	258	684	org/json/JSONException
    //   242	258	671	java/lang/Exception
    //   242	258	654	finally
    //   269	279	131	java/io/IOException
    //   269	279	684	org/json/JSONException
    //   269	279	671	java/lang/Exception
    //   269	279	654	finally
    //   287	296	131	java/io/IOException
    //   287	296	684	org/json/JSONException
    //   287	296	671	java/lang/Exception
    //   287	296	654	finally
    //   304	321	131	java/io/IOException
    //   304	321	684	org/json/JSONException
    //   304	321	671	java/lang/Exception
    //   304	321	654	finally
    //   329	339	131	java/io/IOException
    //   329	339	684	org/json/JSONException
    //   329	339	671	java/lang/Exception
    //   329	339	654	finally
    //   348	353	388	java/io/IOException
    //   362	367	374	java/io/IOException
    //   409	414	437	java/io/IOException
    //   419	424	427	java/io/IOException
    //   483	488	654	finally
    //   493	498	521	java/io/IOException
    //   503	508	511	java/io/IOException
    //   547	552	654	finally
    //   557	562	585	java/io/IOException
    //   567	572	575	java/io/IOException
    //   608	613	626	java/io/IOException
    //   618	623	636	java/io/IOException
  }
}


/* Location:              D:\Code\Crack\dex-tools-2.1-20190905-lanchon\zspns-pcgw-P36417A-0429-dex2jar.jar!\com\zz\sdk\i\bo.class
 * Java compiler version: 6 (50.0)
 * JD-Core Version:       1.1.3
 */